<profile>

<ReportVersion>
<Version>2022.2</Version>
</ReportVersion>

<UserAssignments>
<unit>ns</unit>
<ProductFamily>virtexuplus</ProductFamily>
<Part>xcu55c-fsvh2892-2L-e</Part>
<TopModelName>gru_stack_for_bidirectional_ap_fixed_ap_fixed_33_4_5_3_0_config2_f_s</TopModelName>
<TargetClockPeriod>4.00</TargetClockPeriod>
<ClockUncertainty>1.08</ClockUncertainty>
<FlowTarget>vitis</FlowTarget>
</UserAssignments>

<PerformanceEstimates>
<PipelineType>no</PipelineType>
<SummaryOfTimingAnalysis>
<unit>ns</unit>
<EstimatedClockPeriod>4.019</EstimatedClockPeriod>
</SummaryOfTimingAnalysis>
<SummaryOfOverallLatency>
<unit>clock cycles</unit>
<Best-caseLatency>29712</Best-caseLatency>
<Average-caseLatency>29712</Average-caseLatency>
<Worst-caseLatency>29785</Worst-caseLatency>
<Best-caseRealTimeLatency>0.119 ms</Best-caseRealTimeLatency>
<Average-caseRealTimeLatency>0.119 ms</Average-caseRealTimeLatency>
<Worst-caseRealTimeLatency>0.120 ms</Worst-caseRealTimeLatency>
<Interval-min>29712</Interval-min>
<Interval-max>29785</Interval-max>
</SummaryOfOverallLatency>
<SummaryOfLoopLatency>
<DataPropagation>
<Slack>2.92</Slack>
<TripCount>73</TripCount>
<Latency>
<range>
<min>29711</min>
<max>29784</max>
</range>
</Latency>
<AbsoluteTimeLatency>
<range>
<min>119408</min>
<max>119701</max>
</range>
</AbsoluteTimeLatency>
<IterationLatency>
<range>
<min>407</min>
<max>408</max>
</range>
</IterationLatency>
<InstanceList>
</InstanceList>
</DataPropagation>
</SummaryOfLoopLatency>
</PerformanceEstimates>

<AreaEstimates>
<Resources>
<BRAM_18K>16</BRAM_18K>
<DSP>640</DSP>
<FF>113929</FF>
<LUT>80162</LUT>
<URAM>0</URAM>
</Resources>
<AvailableResources>
<BRAM_18K>4032</BRAM_18K>
<DSP>9024</DSP>
<FF>2607360</FF>
<LUT>1303680</LUT>
<URAM>960</URAM>
</AvailableResources>
</AreaEstimates>

<InterfaceSummary>
<RtlPorts>
<name>ap_clk</name>
<Object>gru_stack_for_bidirectional&lt;ap_fixed,ap_fixed&lt;33,4,5,3,0&gt;,config2_f&gt;</Object>
<Type>return value</Type>
<Scope></Scope>
<IOProtocol>ap_ctrl_hs</IOProtocol>
<IOConfig></IOConfig>
<Dir>in</Dir>
<Bits>1</Bits>
<Attribute>control</Attribute>
</RtlPorts>
<RtlPorts>
<name>ap_rst</name>
<Object>gru_stack_for_bidirectional&lt;ap_fixed,ap_fixed&lt;33,4,5,3,0&gt;,config2_f&gt;</Object>
<Type>return value</Type>
<Scope></Scope>
<IOProtocol>ap_ctrl_hs</IOProtocol>
<IOConfig></IOConfig>
<Dir>in</Dir>
<Bits>1</Bits>
<Attribute>control</Attribute>
</RtlPorts>
<RtlPorts>
<name>ap_start</name>
<Object>gru_stack_for_bidirectional&lt;ap_fixed,ap_fixed&lt;33,4,5,3,0&gt;,config2_f&gt;</Object>
<Type>return value</Type>
<Scope></Scope>
<IOProtocol>ap_ctrl_hs</IOProtocol>
<IOConfig></IOConfig>
<Dir>in</Dir>
<Bits>1</Bits>
<Attribute>control</Attribute>
</RtlPorts>
<RtlPorts>
<name>ap_done</name>
<Object>gru_stack_for_bidirectional&lt;ap_fixed,ap_fixed&lt;33,4,5,3,0&gt;,config2_f&gt;</Object>
<Type>return value</Type>
<Scope></Scope>
<IOProtocol>ap_ctrl_hs</IOProtocol>
<IOConfig></IOConfig>
<Dir>out</Dir>
<Bits>1</Bits>
<Attribute>control</Attribute>
</RtlPorts>
<RtlPorts>
<name>ap_idle</name>
<Object>gru_stack_for_bidirectional&lt;ap_fixed,ap_fixed&lt;33,4,5,3,0&gt;,config2_f&gt;</Object>
<Type>return value</Type>
<Scope></Scope>
<IOProtocol>ap_ctrl_hs</IOProtocol>
<IOConfig></IOConfig>
<Dir>out</Dir>
<Bits>1</Bits>
<Attribute>control</Attribute>
</RtlPorts>
<RtlPorts>
<name>ap_ready</name>
<Object>gru_stack_for_bidirectional&lt;ap_fixed,ap_fixed&lt;33,4,5,3,0&gt;,config2_f&gt;</Object>
<Type>return value</Type>
<Scope></Scope>
<IOProtocol>ap_ctrl_hs</IOProtocol>
<IOConfig></IOConfig>
<Dir>out</Dir>
<Bits>1</Bits>
<Attribute>control</Attribute>
</RtlPorts>
<RtlPorts>
<name>ap_return_0</name>
<Object>gru_stack_for_bidirectional&lt;ap_fixed,ap_fixed&lt;33,4,5,3,0&gt;,config2_f&gt;</Object>
<Type>return value</Type>
<Scope></Scope>
<IOProtocol>ap_ctrl_hs</IOProtocol>
<IOConfig></IOConfig>
<Dir>out</Dir>
<Bits>33</Bits>
<Attribute>data</Attribute>
</RtlPorts>
<RtlPorts>
<name>ap_return_1</name>
<Object>gru_stack_for_bidirectional&lt;ap_fixed,ap_fixed&lt;33,4,5,3,0&gt;,config2_f&gt;</Object>
<Type>return value</Type>
<Scope></Scope>
<IOProtocol>ap_ctrl_hs</IOProtocol>
<IOConfig></IOConfig>
<Dir>out</Dir>
<Bits>33</Bits>
<Attribute>data</Attribute>
</RtlPorts>
<RtlPorts>
<name>ap_return_2</name>
<Object>gru_stack_for_bidirectional&lt;ap_fixed,ap_fixed&lt;33,4,5,3,0&gt;,config2_f&gt;</Object>
<Type>return value</Type>
<Scope></Scope>
<IOProtocol>ap_ctrl_hs</IOProtocol>
<IOConfig></IOConfig>
<Dir>out</Dir>
<Bits>33</Bits>
<Attribute>data</Attribute>
</RtlPorts>
<RtlPorts>
<name>ap_return_3</name>
<Object>gru_stack_for_bidirectional&lt;ap_fixed,ap_fixed&lt;33,4,5,3,0&gt;,config2_f&gt;</Object>
<Type>return value</Type>
<Scope></Scope>
<IOProtocol>ap_ctrl_hs</IOProtocol>
<IOConfig></IOConfig>
<Dir>out</Dir>
<Bits>33</Bits>
<Attribute>data</Attribute>
</RtlPorts>
<RtlPorts>
<name>ap_return_4</name>
<Object>gru_stack_for_bidirectional&lt;ap_fixed,ap_fixed&lt;33,4,5,3,0&gt;,config2_f&gt;</Object>
<Type>return value</Type>
<Scope></Scope>
<IOProtocol>ap_ctrl_hs</IOProtocol>
<IOConfig></IOConfig>
<Dir>out</Dir>
<Bits>33</Bits>
<Attribute>data</Attribute>
</RtlPorts>
<RtlPorts>
<name>ap_return_5</name>
<Object>gru_stack_for_bidirectional&lt;ap_fixed,ap_fixed&lt;33,4,5,3,0&gt;,config2_f&gt;</Object>
<Type>return value</Type>
<Scope></Scope>
<IOProtocol>ap_ctrl_hs</IOProtocol>
<IOConfig></IOConfig>
<Dir>out</Dir>
<Bits>33</Bits>
<Attribute>data</Attribute>
</RtlPorts>
<RtlPorts>
<name>ap_return_6</name>
<Object>gru_stack_for_bidirectional&lt;ap_fixed,ap_fixed&lt;33,4,5,3,0&gt;,config2_f&gt;</Object>
<Type>return value</Type>
<Scope></Scope>
<IOProtocol>ap_ctrl_hs</IOProtocol>
<IOConfig></IOConfig>
<Dir>out</Dir>
<Bits>33</Bits>
<Attribute>data</Attribute>
</RtlPorts>
<RtlPorts>
<name>ap_return_7</name>
<Object>gru_stack_for_bidirectional&lt;ap_fixed,ap_fixed&lt;33,4,5,3,0&gt;,config2_f&gt;</Object>
<Type>return value</Type>
<Scope></Scope>
<IOProtocol>ap_ctrl_hs</IOProtocol>
<IOConfig></IOConfig>
<Dir>out</Dir>
<Bits>33</Bits>
<Attribute>data</Attribute>
</RtlPorts>
<RtlPorts>
<name>ap_return_8</name>
<Object>gru_stack_for_bidirectional&lt;ap_fixed,ap_fixed&lt;33,4,5,3,0&gt;,config2_f&gt;</Object>
<Type>return value</Type>
<Scope></Scope>
<IOProtocol>ap_ctrl_hs</IOProtocol>
<IOConfig></IOConfig>
<Dir>out</Dir>
<Bits>33</Bits>
<Attribute>data</Attribute>
</RtlPorts>
<RtlPorts>
<name>ap_return_9</name>
<Object>gru_stack_for_bidirectional&lt;ap_fixed,ap_fixed&lt;33,4,5,3,0&gt;,config2_f&gt;</Object>
<Type>return value</Type>
<Scope></Scope>
<IOProtocol>ap_ctrl_hs</IOProtocol>
<IOConfig></IOConfig>
<Dir>out</Dir>
<Bits>33</Bits>
<Attribute>data</Attribute>
</RtlPorts>
<RtlPorts>
<name>ap_return_10</name>
<Object>gru_stack_for_bidirectional&lt;ap_fixed,ap_fixed&lt;33,4,5,3,0&gt;,config2_f&gt;</Object>
<Type>return value</Type>
<Scope></Scope>
<IOProtocol>ap_ctrl_hs</IOProtocol>
<IOConfig></IOConfig>
<Dir>out</Dir>
<Bits>33</Bits>
<Attribute>data</Attribute>
</RtlPorts>
<RtlPorts>
<name>ap_return_11</name>
<Object>gru_stack_for_bidirectional&lt;ap_fixed,ap_fixed&lt;33,4,5,3,0&gt;,config2_f&gt;</Object>
<Type>return value</Type>
<Scope></Scope>
<IOProtocol>ap_ctrl_hs</IOProtocol>
<IOConfig></IOConfig>
<Dir>out</Dir>
<Bits>33</Bits>
<Attribute>data</Attribute>
</RtlPorts>
<RtlPorts>
<name>ap_return_12</name>
<Object>gru_stack_for_bidirectional&lt;ap_fixed,ap_fixed&lt;33,4,5,3,0&gt;,config2_f&gt;</Object>
<Type>return value</Type>
<Scope></Scope>
<IOProtocol>ap_ctrl_hs</IOProtocol>
<IOConfig></IOConfig>
<Dir>out</Dir>
<Bits>33</Bits>
<Attribute>data</Attribute>
</RtlPorts>
<RtlPorts>
<name>ap_return_13</name>
<Object>gru_stack_for_bidirectional&lt;ap_fixed,ap_fixed&lt;33,4,5,3,0&gt;,config2_f&gt;</Object>
<Type>return value</Type>
<Scope></Scope>
<IOProtocol>ap_ctrl_hs</IOProtocol>
<IOConfig></IOConfig>
<Dir>out</Dir>
<Bits>33</Bits>
<Attribute>data</Attribute>
</RtlPorts>
<RtlPorts>
<name>ap_return_14</name>
<Object>gru_stack_for_bidirectional&lt;ap_fixed,ap_fixed&lt;33,4,5,3,0&gt;,config2_f&gt;</Object>
<Type>return value</Type>
<Scope></Scope>
<IOProtocol>ap_ctrl_hs</IOProtocol>
<IOConfig></IOConfig>
<Dir>out</Dir>
<Bits>33</Bits>
<Attribute>data</Attribute>
</RtlPorts>
<RtlPorts>
<name>ap_return_15</name>
<Object>gru_stack_for_bidirectional&lt;ap_fixed,ap_fixed&lt;33,4,5,3,0&gt;,config2_f&gt;</Object>
<Type>return value</Type>
<Scope></Scope>
<IOProtocol>ap_ctrl_hs</IOProtocol>
<IOConfig></IOConfig>
<Dir>out</Dir>
<Bits>33</Bits>
<Attribute>data</Attribute>
</RtlPorts>
<RtlPorts>
<name>ap_return_16</name>
<Object>gru_stack_for_bidirectional&lt;ap_fixed,ap_fixed&lt;33,4,5,3,0&gt;,config2_f&gt;</Object>
<Type>return value</Type>
<Scope></Scope>
<IOProtocol>ap_ctrl_hs</IOProtocol>
<IOConfig></IOConfig>
<Dir>out</Dir>
<Bits>33</Bits>
<Attribute>data</Attribute>
</RtlPorts>
<RtlPorts>
<name>ap_return_17</name>
<Object>gru_stack_for_bidirectional&lt;ap_fixed,ap_fixed&lt;33,4,5,3,0&gt;,config2_f&gt;</Object>
<Type>return value</Type>
<Scope></Scope>
<IOProtocol>ap_ctrl_hs</IOProtocol>
<IOConfig></IOConfig>
<Dir>out</Dir>
<Bits>33</Bits>
<Attribute>data</Attribute>
</RtlPorts>
<RtlPorts>
<name>ap_return_18</name>
<Object>gru_stack_for_bidirectional&lt;ap_fixed,ap_fixed&lt;33,4,5,3,0&gt;,config2_f&gt;</Object>
<Type>return value</Type>
<Scope></Scope>
<IOProtocol>ap_ctrl_hs</IOProtocol>
<IOConfig></IOConfig>
<Dir>out</Dir>
<Bits>33</Bits>
<Attribute>data</Attribute>
</RtlPorts>
<RtlPorts>
<name>ap_return_19</name>
<Object>gru_stack_for_bidirectional&lt;ap_fixed,ap_fixed&lt;33,4,5,3,0&gt;,config2_f&gt;</Object>
<Type>return value</Type>
<Scope></Scope>
<IOProtocol>ap_ctrl_hs</IOProtocol>
<IOConfig></IOConfig>
<Dir>out</Dir>
<Bits>33</Bits>
<Attribute>data</Attribute>
</RtlPorts>
<RtlPorts>
<name>ap_return_20</name>
<Object>gru_stack_for_bidirectional&lt;ap_fixed,ap_fixed&lt;33,4,5,3,0&gt;,config2_f&gt;</Object>
<Type>return value</Type>
<Scope></Scope>
<IOProtocol>ap_ctrl_hs</IOProtocol>
<IOConfig></IOConfig>
<Dir>out</Dir>
<Bits>33</Bits>
<Attribute>data</Attribute>
</RtlPorts>
<RtlPorts>
<name>ap_return_21</name>
<Object>gru_stack_for_bidirectional&lt;ap_fixed,ap_fixed&lt;33,4,5,3,0&gt;,config2_f&gt;</Object>
<Type>return value</Type>
<Scope></Scope>
<IOProtocol>ap_ctrl_hs</IOProtocol>
<IOConfig></IOConfig>
<Dir>out</Dir>
<Bits>33</Bits>
<Attribute>data</Attribute>
</RtlPorts>
<RtlPorts>
<name>ap_return_22</name>
<Object>gru_stack_for_bidirectional&lt;ap_fixed,ap_fixed&lt;33,4,5,3,0&gt;,config2_f&gt;</Object>
<Type>return value</Type>
<Scope></Scope>
<IOProtocol>ap_ctrl_hs</IOProtocol>
<IOConfig></IOConfig>
<Dir>out</Dir>
<Bits>33</Bits>
<Attribute>data</Attribute>
</RtlPorts>
<RtlPorts>
<name>ap_return_23</name>
<Object>gru_stack_for_bidirectional&lt;ap_fixed,ap_fixed&lt;33,4,5,3,0&gt;,config2_f&gt;</Object>
<Type>return value</Type>
<Scope></Scope>
<IOProtocol>ap_ctrl_hs</IOProtocol>
<IOConfig></IOConfig>
<Dir>out</Dir>
<Bits>33</Bits>
<Attribute>data</Attribute>
</RtlPorts>
<RtlPorts>
<name>ap_return_24</name>
<Object>gru_stack_for_bidirectional&lt;ap_fixed,ap_fixed&lt;33,4,5,3,0&gt;,config2_f&gt;</Object>
<Type>return value</Type>
<Scope></Scope>
<IOProtocol>ap_ctrl_hs</IOProtocol>
<IOConfig></IOConfig>
<Dir>out</Dir>
<Bits>33</Bits>
<Attribute>data</Attribute>
</RtlPorts>
<RtlPorts>
<name>ap_return_25</name>
<Object>gru_stack_for_bidirectional&lt;ap_fixed,ap_fixed&lt;33,4,5,3,0&gt;,config2_f&gt;</Object>
<Type>return value</Type>
<Scope></Scope>
<IOProtocol>ap_ctrl_hs</IOProtocol>
<IOConfig></IOConfig>
<Dir>out</Dir>
<Bits>33</Bits>
<Attribute>data</Attribute>
</RtlPorts>
<RtlPorts>
<name>ap_return_26</name>
<Object>gru_stack_for_bidirectional&lt;ap_fixed,ap_fixed&lt;33,4,5,3,0&gt;,config2_f&gt;</Object>
<Type>return value</Type>
<Scope></Scope>
<IOProtocol>ap_ctrl_hs</IOProtocol>
<IOConfig></IOConfig>
<Dir>out</Dir>
<Bits>33</Bits>
<Attribute>data</Attribute>
</RtlPorts>
<RtlPorts>
<name>ap_return_27</name>
<Object>gru_stack_for_bidirectional&lt;ap_fixed,ap_fixed&lt;33,4,5,3,0&gt;,config2_f&gt;</Object>
<Type>return value</Type>
<Scope></Scope>
<IOProtocol>ap_ctrl_hs</IOProtocol>
<IOConfig></IOConfig>
<Dir>out</Dir>
<Bits>33</Bits>
<Attribute>data</Attribute>
</RtlPorts>
<RtlPorts>
<name>ap_return_28</name>
<Object>gru_stack_for_bidirectional&lt;ap_fixed,ap_fixed&lt;33,4,5,3,0&gt;,config2_f&gt;</Object>
<Type>return value</Type>
<Scope></Scope>
<IOProtocol>ap_ctrl_hs</IOProtocol>
<IOConfig></IOConfig>
<Dir>out</Dir>
<Bits>33</Bits>
<Attribute>data</Attribute>
</RtlPorts>
<RtlPorts>
<name>ap_return_29</name>
<Object>gru_stack_for_bidirectional&lt;ap_fixed,ap_fixed&lt;33,4,5,3,0&gt;,config2_f&gt;</Object>
<Type>return value</Type>
<Scope></Scope>
<IOProtocol>ap_ctrl_hs</IOProtocol>
<IOConfig></IOConfig>
<Dir>out</Dir>
<Bits>33</Bits>
<Attribute>data</Attribute>
</RtlPorts>
<RtlPorts>
<name>ap_return_30</name>
<Object>gru_stack_for_bidirectional&lt;ap_fixed,ap_fixed&lt;33,4,5,3,0&gt;,config2_f&gt;</Object>
<Type>return value</Type>
<Scope></Scope>
<IOProtocol>ap_ctrl_hs</IOProtocol>
<IOConfig></IOConfig>
<Dir>out</Dir>
<Bits>33</Bits>
<Attribute>data</Attribute>
</RtlPorts>
<RtlPorts>
<name>ap_return_31</name>
<Object>gru_stack_for_bidirectional&lt;ap_fixed,ap_fixed&lt;33,4,5,3,0&gt;,config2_f&gt;</Object>
<Type>return value</Type>
<Scope></Scope>
<IOProtocol>ap_ctrl_hs</IOProtocol>
<IOConfig></IOConfig>
<Dir>out</Dir>
<Bits>33</Bits>
<Attribute>data</Attribute>
</RtlPorts>
<RtlPorts>
<name>ap_return_32</name>
<Object>gru_stack_for_bidirectional&lt;ap_fixed,ap_fixed&lt;33,4,5,3,0&gt;,config2_f&gt;</Object>
<Type>return value</Type>
<Scope></Scope>
<IOProtocol>ap_ctrl_hs</IOProtocol>
<IOConfig></IOConfig>
<Dir>out</Dir>
<Bits>33</Bits>
<Attribute>data</Attribute>
</RtlPorts>
<RtlPorts>
<name>ap_return_33</name>
<Object>gru_stack_for_bidirectional&lt;ap_fixed,ap_fixed&lt;33,4,5,3,0&gt;,config2_f&gt;</Object>
<Type>return value</Type>
<Scope></Scope>
<IOProtocol>ap_ctrl_hs</IOProtocol>
<IOConfig></IOConfig>
<Dir>out</Dir>
<Bits>33</Bits>
<Attribute>data</Attribute>
</RtlPorts>
<RtlPorts>
<name>ap_return_34</name>
<Object>gru_stack_for_bidirectional&lt;ap_fixed,ap_fixed&lt;33,4,5,3,0&gt;,config2_f&gt;</Object>
<Type>return value</Type>
<Scope></Scope>
<IOProtocol>ap_ctrl_hs</IOProtocol>
<IOConfig></IOConfig>
<Dir>out</Dir>
<Bits>33</Bits>
<Attribute>data</Attribute>
</RtlPorts>
<RtlPorts>
<name>ap_return_35</name>
<Object>gru_stack_for_bidirectional&lt;ap_fixed,ap_fixed&lt;33,4,5,3,0&gt;,config2_f&gt;</Object>
<Type>return value</Type>
<Scope></Scope>
<IOProtocol>ap_ctrl_hs</IOProtocol>
<IOConfig></IOConfig>
<Dir>out</Dir>
<Bits>33</Bits>
<Attribute>data</Attribute>
</RtlPorts>
<RtlPorts>
<name>ap_return_36</name>
<Object>gru_stack_for_bidirectional&lt;ap_fixed,ap_fixed&lt;33,4,5,3,0&gt;,config2_f&gt;</Object>
<Type>return value</Type>
<Scope></Scope>
<IOProtocol>ap_ctrl_hs</IOProtocol>
<IOConfig></IOConfig>
<Dir>out</Dir>
<Bits>33</Bits>
<Attribute>data</Attribute>
</RtlPorts>
<RtlPorts>
<name>ap_return_37</name>
<Object>gru_stack_for_bidirectional&lt;ap_fixed,ap_fixed&lt;33,4,5,3,0&gt;,config2_f&gt;</Object>
<Type>return value</Type>
<Scope></Scope>
<IOProtocol>ap_ctrl_hs</IOProtocol>
<IOConfig></IOConfig>
<Dir>out</Dir>
<Bits>33</Bits>
<Attribute>data</Attribute>
</RtlPorts>
<RtlPorts>
<name>ap_return_38</name>
<Object>gru_stack_for_bidirectional&lt;ap_fixed,ap_fixed&lt;33,4,5,3,0&gt;,config2_f&gt;</Object>
<Type>return value</Type>
<Scope></Scope>
<IOProtocol>ap_ctrl_hs</IOProtocol>
<IOConfig></IOConfig>
<Dir>out</Dir>
<Bits>33</Bits>
<Attribute>data</Attribute>
</RtlPorts>
<RtlPorts>
<name>ap_return_39</name>
<Object>gru_stack_for_bidirectional&lt;ap_fixed,ap_fixed&lt;33,4,5,3,0&gt;,config2_f&gt;</Object>
<Type>return value</Type>
<Scope></Scope>
<IOProtocol>ap_ctrl_hs</IOProtocol>
<IOConfig></IOConfig>
<Dir>out</Dir>
<Bits>33</Bits>
<Attribute>data</Attribute>
</RtlPorts>
<RtlPorts>
<name>ap_return_40</name>
<Object>gru_stack_for_bidirectional&lt;ap_fixed,ap_fixed&lt;33,4,5,3,0&gt;,config2_f&gt;</Object>
<Type>return value</Type>
<Scope></Scope>
<IOProtocol>ap_ctrl_hs</IOProtocol>
<IOConfig></IOConfig>
<Dir>out</Dir>
<Bits>33</Bits>
<Attribute>data</Attribute>
</RtlPorts>
<RtlPorts>
<name>ap_return_41</name>
<Object>gru_stack_for_bidirectional&lt;ap_fixed,ap_fixed&lt;33,4,5,3,0&gt;,config2_f&gt;</Object>
<Type>return value</Type>
<Scope></Scope>
<IOProtocol>ap_ctrl_hs</IOProtocol>
<IOConfig></IOConfig>
<Dir>out</Dir>
<Bits>33</Bits>
<Attribute>data</Attribute>
</RtlPorts>
<RtlPorts>
<name>ap_return_42</name>
<Object>gru_stack_for_bidirectional&lt;ap_fixed,ap_fixed&lt;33,4,5,3,0&gt;,config2_f&gt;</Object>
<Type>return value</Type>
<Scope></Scope>
<IOProtocol>ap_ctrl_hs</IOProtocol>
<IOConfig></IOConfig>
<Dir>out</Dir>
<Bits>33</Bits>
<Attribute>data</Attribute>
</RtlPorts>
<RtlPorts>
<name>ap_return_43</name>
<Object>gru_stack_for_bidirectional&lt;ap_fixed,ap_fixed&lt;33,4,5,3,0&gt;,config2_f&gt;</Object>
<Type>return value</Type>
<Scope></Scope>
<IOProtocol>ap_ctrl_hs</IOProtocol>
<IOConfig></IOConfig>
<Dir>out</Dir>
<Bits>33</Bits>
<Attribute>data</Attribute>
</RtlPorts>
<RtlPorts>
<name>ap_return_44</name>
<Object>gru_stack_for_bidirectional&lt;ap_fixed,ap_fixed&lt;33,4,5,3,0&gt;,config2_f&gt;</Object>
<Type>return value</Type>
<Scope></Scope>
<IOProtocol>ap_ctrl_hs</IOProtocol>
<IOConfig></IOConfig>
<Dir>out</Dir>
<Bits>33</Bits>
<Attribute>data</Attribute>
</RtlPorts>
<RtlPorts>
<name>ap_return_45</name>
<Object>gru_stack_for_bidirectional&lt;ap_fixed,ap_fixed&lt;33,4,5,3,0&gt;,config2_f&gt;</Object>
<Type>return value</Type>
<Scope></Scope>
<IOProtocol>ap_ctrl_hs</IOProtocol>
<IOConfig></IOConfig>
<Dir>out</Dir>
<Bits>33</Bits>
<Attribute>data</Attribute>
</RtlPorts>
<RtlPorts>
<name>ap_return_46</name>
<Object>gru_stack_for_bidirectional&lt;ap_fixed,ap_fixed&lt;33,4,5,3,0&gt;,config2_f&gt;</Object>
<Type>return value</Type>
<Scope></Scope>
<IOProtocol>ap_ctrl_hs</IOProtocol>
<IOConfig></IOConfig>
<Dir>out</Dir>
<Bits>33</Bits>
<Attribute>data</Attribute>
</RtlPorts>
<RtlPorts>
<name>ap_return_47</name>
<Object>gru_stack_for_bidirectional&lt;ap_fixed,ap_fixed&lt;33,4,5,3,0&gt;,config2_f&gt;</Object>
<Type>return value</Type>
<Scope></Scope>
<IOProtocol>ap_ctrl_hs</IOProtocol>
<IOConfig></IOConfig>
<Dir>out</Dir>
<Bits>33</Bits>
<Attribute>data</Attribute>
</RtlPorts>
<RtlPorts>
<name>ap_return_48</name>
<Object>gru_stack_for_bidirectional&lt;ap_fixed,ap_fixed&lt;33,4,5,3,0&gt;,config2_f&gt;</Object>
<Type>return value</Type>
<Scope></Scope>
<IOProtocol>ap_ctrl_hs</IOProtocol>
<IOConfig></IOConfig>
<Dir>out</Dir>
<Bits>33</Bits>
<Attribute>data</Attribute>
</RtlPorts>
<RtlPorts>
<name>ap_return_49</name>
<Object>gru_stack_for_bidirectional&lt;ap_fixed,ap_fixed&lt;33,4,5,3,0&gt;,config2_f&gt;</Object>
<Type>return value</Type>
<Scope></Scope>
<IOProtocol>ap_ctrl_hs</IOProtocol>
<IOConfig></IOConfig>
<Dir>out</Dir>
<Bits>33</Bits>
<Attribute>data</Attribute>
</RtlPorts>
<RtlPorts>
<name>ap_return_50</name>
<Object>gru_stack_for_bidirectional&lt;ap_fixed,ap_fixed&lt;33,4,5,3,0&gt;,config2_f&gt;</Object>
<Type>return value</Type>
<Scope></Scope>
<IOProtocol>ap_ctrl_hs</IOProtocol>
<IOConfig></IOConfig>
<Dir>out</Dir>
<Bits>33</Bits>
<Attribute>data</Attribute>
</RtlPorts>
<RtlPorts>
<name>ap_return_51</name>
<Object>gru_stack_for_bidirectional&lt;ap_fixed,ap_fixed&lt;33,4,5,3,0&gt;,config2_f&gt;</Object>
<Type>return value</Type>
<Scope></Scope>
<IOProtocol>ap_ctrl_hs</IOProtocol>
<IOConfig></IOConfig>
<Dir>out</Dir>
<Bits>33</Bits>
<Attribute>data</Attribute>
</RtlPorts>
<RtlPorts>
<name>ap_return_52</name>
<Object>gru_stack_for_bidirectional&lt;ap_fixed,ap_fixed&lt;33,4,5,3,0&gt;,config2_f&gt;</Object>
<Type>return value</Type>
<Scope></Scope>
<IOProtocol>ap_ctrl_hs</IOProtocol>
<IOConfig></IOConfig>
<Dir>out</Dir>
<Bits>33</Bits>
<Attribute>data</Attribute>
</RtlPorts>
<RtlPorts>
<name>ap_return_53</name>
<Object>gru_stack_for_bidirectional&lt;ap_fixed,ap_fixed&lt;33,4,5,3,0&gt;,config2_f&gt;</Object>
<Type>return value</Type>
<Scope></Scope>
<IOProtocol>ap_ctrl_hs</IOProtocol>
<IOConfig></IOConfig>
<Dir>out</Dir>
<Bits>33</Bits>
<Attribute>data</Attribute>
</RtlPorts>
<RtlPorts>
<name>ap_return_54</name>
<Object>gru_stack_for_bidirectional&lt;ap_fixed,ap_fixed&lt;33,4,5,3,0&gt;,config2_f&gt;</Object>
<Type>return value</Type>
<Scope></Scope>
<IOProtocol>ap_ctrl_hs</IOProtocol>
<IOConfig></IOConfig>
<Dir>out</Dir>
<Bits>33</Bits>
<Attribute>data</Attribute>
</RtlPorts>
<RtlPorts>
<name>ap_return_55</name>
<Object>gru_stack_for_bidirectional&lt;ap_fixed,ap_fixed&lt;33,4,5,3,0&gt;,config2_f&gt;</Object>
<Type>return value</Type>
<Scope></Scope>
<IOProtocol>ap_ctrl_hs</IOProtocol>
<IOConfig></IOConfig>
<Dir>out</Dir>
<Bits>33</Bits>
<Attribute>data</Attribute>
</RtlPorts>
<RtlPorts>
<name>ap_return_56</name>
<Object>gru_stack_for_bidirectional&lt;ap_fixed,ap_fixed&lt;33,4,5,3,0&gt;,config2_f&gt;</Object>
<Type>return value</Type>
<Scope></Scope>
<IOProtocol>ap_ctrl_hs</IOProtocol>
<IOConfig></IOConfig>
<Dir>out</Dir>
<Bits>33</Bits>
<Attribute>data</Attribute>
</RtlPorts>
<RtlPorts>
<name>ap_return_57</name>
<Object>gru_stack_for_bidirectional&lt;ap_fixed,ap_fixed&lt;33,4,5,3,0&gt;,config2_f&gt;</Object>
<Type>return value</Type>
<Scope></Scope>
<IOProtocol>ap_ctrl_hs</IOProtocol>
<IOConfig></IOConfig>
<Dir>out</Dir>
<Bits>33</Bits>
<Attribute>data</Attribute>
</RtlPorts>
<RtlPorts>
<name>ap_return_58</name>
<Object>gru_stack_for_bidirectional&lt;ap_fixed,ap_fixed&lt;33,4,5,3,0&gt;,config2_f&gt;</Object>
<Type>return value</Type>
<Scope></Scope>
<IOProtocol>ap_ctrl_hs</IOProtocol>
<IOConfig></IOConfig>
<Dir>out</Dir>
<Bits>33</Bits>
<Attribute>data</Attribute>
</RtlPorts>
<RtlPorts>
<name>ap_return_59</name>
<Object>gru_stack_for_bidirectional&lt;ap_fixed,ap_fixed&lt;33,4,5,3,0&gt;,config2_f&gt;</Object>
<Type>return value</Type>
<Scope></Scope>
<IOProtocol>ap_ctrl_hs</IOProtocol>
<IOConfig></IOConfig>
<Dir>out</Dir>
<Bits>33</Bits>
<Attribute>data</Attribute>
</RtlPorts>
<RtlPorts>
<name>ap_return_60</name>
<Object>gru_stack_for_bidirectional&lt;ap_fixed,ap_fixed&lt;33,4,5,3,0&gt;,config2_f&gt;</Object>
<Type>return value</Type>
<Scope></Scope>
<IOProtocol>ap_ctrl_hs</IOProtocol>
<IOConfig></IOConfig>
<Dir>out</Dir>
<Bits>33</Bits>
<Attribute>data</Attribute>
</RtlPorts>
<RtlPorts>
<name>ap_return_61</name>
<Object>gru_stack_for_bidirectional&lt;ap_fixed,ap_fixed&lt;33,4,5,3,0&gt;,config2_f&gt;</Object>
<Type>return value</Type>
<Scope></Scope>
<IOProtocol>ap_ctrl_hs</IOProtocol>
<IOConfig></IOConfig>
<Dir>out</Dir>
<Bits>33</Bits>
<Attribute>data</Attribute>
</RtlPorts>
<RtlPorts>
<name>ap_return_62</name>
<Object>gru_stack_for_bidirectional&lt;ap_fixed,ap_fixed&lt;33,4,5,3,0&gt;,config2_f&gt;</Object>
<Type>return value</Type>
<Scope></Scope>
<IOProtocol>ap_ctrl_hs</IOProtocol>
<IOConfig></IOConfig>
<Dir>out</Dir>
<Bits>33</Bits>
<Attribute>data</Attribute>
</RtlPorts>
<RtlPorts>
<name>ap_return_63</name>
<Object>gru_stack_for_bidirectional&lt;ap_fixed,ap_fixed&lt;33,4,5,3,0&gt;,config2_f&gt;</Object>
<Type>return value</Type>
<Scope></Scope>
<IOProtocol>ap_ctrl_hs</IOProtocol>
<IOConfig></IOConfig>
<Dir>out</Dir>
<Bits>33</Bits>
<Attribute>data</Attribute>
</RtlPorts>
<RtlPorts>
<name>data_0_address0</name>
<Object>data_0</Object>
<Type>array</Type>
<Scope></Scope>
<IOProtocol>ap_memory</IOProtocol>
<IOConfig></IOConfig>
<Dir>out</Dir>
<Bits>7</Bits>
<Attribute>address</Attribute>
</RtlPorts>
<RtlPorts>
<name>data_0_ce0</name>
<Object>data_0</Object>
<Type>array</Type>
<Scope></Scope>
<IOProtocol>ap_memory</IOProtocol>
<IOConfig></IOConfig>
<Dir>out</Dir>
<Bits>1</Bits>
<Attribute>control</Attribute>
</RtlPorts>
<RtlPorts>
<name>data_0_q0</name>
<Object>data_0</Object>
<Type>array</Type>
<Scope></Scope>
<IOProtocol>ap_memory</IOProtocol>
<IOConfig></IOConfig>
<Dir>in</Dir>
<Bits>16</Bits>
<Attribute>data</Attribute>
</RtlPorts>
<RtlPorts>
<name>data_1_address0</name>
<Object>data_1</Object>
<Type>array</Type>
<Scope></Scope>
<IOProtocol>ap_memory</IOProtocol>
<IOConfig></IOConfig>
<Dir>out</Dir>
<Bits>7</Bits>
<Attribute>address</Attribute>
</RtlPorts>
<RtlPorts>
<name>data_1_ce0</name>
<Object>data_1</Object>
<Type>array</Type>
<Scope></Scope>
<IOProtocol>ap_memory</IOProtocol>
<IOConfig></IOConfig>
<Dir>out</Dir>
<Bits>1</Bits>
<Attribute>control</Attribute>
</RtlPorts>
<RtlPorts>
<name>data_1_q0</name>
<Object>data_1</Object>
<Type>array</Type>
<Scope></Scope>
<IOProtocol>ap_memory</IOProtocol>
<IOConfig></IOConfig>
<Dir>in</Dir>
<Bits>16</Bits>
<Attribute>data</Attribute>
</RtlPorts>
<RtlPorts>
<name>data_2_address0</name>
<Object>data_2</Object>
<Type>array</Type>
<Scope></Scope>
<IOProtocol>ap_memory</IOProtocol>
<IOConfig></IOConfig>
<Dir>out</Dir>
<Bits>7</Bits>
<Attribute>address</Attribute>
</RtlPorts>
<RtlPorts>
<name>data_2_ce0</name>
<Object>data_2</Object>
<Type>array</Type>
<Scope></Scope>
<IOProtocol>ap_memory</IOProtocol>
<IOConfig></IOConfig>
<Dir>out</Dir>
<Bits>1</Bits>
<Attribute>control</Attribute>
</RtlPorts>
<RtlPorts>
<name>data_2_q0</name>
<Object>data_2</Object>
<Type>array</Type>
<Scope></Scope>
<IOProtocol>ap_memory</IOProtocol>
<IOConfig></IOConfig>
<Dir>in</Dir>
<Bits>16</Bits>
<Attribute>data</Attribute>
</RtlPorts>
<RtlPorts>
<name>data_3_address0</name>
<Object>data_3</Object>
<Type>array</Type>
<Scope></Scope>
<IOProtocol>ap_memory</IOProtocol>
<IOConfig></IOConfig>
<Dir>out</Dir>
<Bits>7</Bits>
<Attribute>address</Attribute>
</RtlPorts>
<RtlPorts>
<name>data_3_ce0</name>
<Object>data_3</Object>
<Type>array</Type>
<Scope></Scope>
<IOProtocol>ap_memory</IOProtocol>
<IOConfig></IOConfig>
<Dir>out</Dir>
<Bits>1</Bits>
<Attribute>control</Attribute>
</RtlPorts>
<RtlPorts>
<name>data_3_q0</name>
<Object>data_3</Object>
<Type>array</Type>
<Scope></Scope>
<IOProtocol>ap_memory</IOProtocol>
<IOConfig></IOConfig>
<Dir>in</Dir>
<Bits>16</Bits>
<Attribute>data</Attribute>
</RtlPorts>
<RtlPorts>
<name>data_4_address0</name>
<Object>data_4</Object>
<Type>array</Type>
<Scope></Scope>
<IOProtocol>ap_memory</IOProtocol>
<IOConfig></IOConfig>
<Dir>out</Dir>
<Bits>7</Bits>
<Attribute>address</Attribute>
</RtlPorts>
<RtlPorts>
<name>data_4_ce0</name>
<Object>data_4</Object>
<Type>array</Type>
<Scope></Scope>
<IOProtocol>ap_memory</IOProtocol>
<IOConfig></IOConfig>
<Dir>out</Dir>
<Bits>1</Bits>
<Attribute>control</Attribute>
</RtlPorts>
<RtlPorts>
<name>data_4_q0</name>
<Object>data_4</Object>
<Type>array</Type>
<Scope></Scope>
<IOProtocol>ap_memory</IOProtocol>
<IOConfig></IOConfig>
<Dir>in</Dir>
<Bits>16</Bits>
<Attribute>data</Attribute>
</RtlPorts>
<RtlPorts>
<name>data_5_address0</name>
<Object>data_5</Object>
<Type>array</Type>
<Scope></Scope>
<IOProtocol>ap_memory</IOProtocol>
<IOConfig></IOConfig>
<Dir>out</Dir>
<Bits>7</Bits>
<Attribute>address</Attribute>
</RtlPorts>
<RtlPorts>
<name>data_5_ce0</name>
<Object>data_5</Object>
<Type>array</Type>
<Scope></Scope>
<IOProtocol>ap_memory</IOProtocol>
<IOConfig></IOConfig>
<Dir>out</Dir>
<Bits>1</Bits>
<Attribute>control</Attribute>
</RtlPorts>
<RtlPorts>
<name>data_5_q0</name>
<Object>data_5</Object>
<Type>array</Type>
<Scope></Scope>
<IOProtocol>ap_memory</IOProtocol>
<IOConfig></IOConfig>
<Dir>in</Dir>
<Bits>16</Bits>
<Attribute>data</Attribute>
</RtlPorts>
<RtlPorts>
<name>data_6_address0</name>
<Object>data_6</Object>
<Type>array</Type>
<Scope></Scope>
<IOProtocol>ap_memory</IOProtocol>
<IOConfig></IOConfig>
<Dir>out</Dir>
<Bits>7</Bits>
<Attribute>address</Attribute>
</RtlPorts>
<RtlPorts>
<name>data_6_ce0</name>
<Object>data_6</Object>
<Type>array</Type>
<Scope></Scope>
<IOProtocol>ap_memory</IOProtocol>
<IOConfig></IOConfig>
<Dir>out</Dir>
<Bits>1</Bits>
<Attribute>control</Attribute>
</RtlPorts>
<RtlPorts>
<name>data_6_q0</name>
<Object>data_6</Object>
<Type>array</Type>
<Scope></Scope>
<IOProtocol>ap_memory</IOProtocol>
<IOConfig></IOConfig>
<Dir>in</Dir>
<Bits>16</Bits>
<Attribute>data</Attribute>
</RtlPorts>
<RtlPorts>
<name>data_7_address0</name>
<Object>data_7</Object>
<Type>array</Type>
<Scope></Scope>
<IOProtocol>ap_memory</IOProtocol>
<IOConfig></IOConfig>
<Dir>out</Dir>
<Bits>7</Bits>
<Attribute>address</Attribute>
</RtlPorts>
<RtlPorts>
<name>data_7_ce0</name>
<Object>data_7</Object>
<Type>array</Type>
<Scope></Scope>
<IOProtocol>ap_memory</IOProtocol>
<IOConfig></IOConfig>
<Dir>out</Dir>
<Bits>1</Bits>
<Attribute>control</Attribute>
</RtlPorts>
<RtlPorts>
<name>data_7_q0</name>
<Object>data_7</Object>
<Type>array</Type>
<Scope></Scope>
<IOProtocol>ap_memory</IOProtocol>
<IOConfig></IOConfig>
<Dir>in</Dir>
<Bits>16</Bits>
<Attribute>data</Attribute>
</RtlPorts>
<RtlPorts>
<name>data_8_address0</name>
<Object>data_8</Object>
<Type>array</Type>
<Scope></Scope>
<IOProtocol>ap_memory</IOProtocol>
<IOConfig></IOConfig>
<Dir>out</Dir>
<Bits>7</Bits>
<Attribute>address</Attribute>
</RtlPorts>
<RtlPorts>
<name>data_8_ce0</name>
<Object>data_8</Object>
<Type>array</Type>
<Scope></Scope>
<IOProtocol>ap_memory</IOProtocol>
<IOConfig></IOConfig>
<Dir>out</Dir>
<Bits>1</Bits>
<Attribute>control</Attribute>
</RtlPorts>
<RtlPorts>
<name>data_8_q0</name>
<Object>data_8</Object>
<Type>array</Type>
<Scope></Scope>
<IOProtocol>ap_memory</IOProtocol>
<IOConfig></IOConfig>
<Dir>in</Dir>
<Bits>16</Bits>
<Attribute>data</Attribute>
</RtlPorts>
<RtlPorts>
<name>data_9_address0</name>
<Object>data_9</Object>
<Type>array</Type>
<Scope></Scope>
<IOProtocol>ap_memory</IOProtocol>
<IOConfig></IOConfig>
<Dir>out</Dir>
<Bits>7</Bits>
<Attribute>address</Attribute>
</RtlPorts>
<RtlPorts>
<name>data_9_ce0</name>
<Object>data_9</Object>
<Type>array</Type>
<Scope></Scope>
<IOProtocol>ap_memory</IOProtocol>
<IOConfig></IOConfig>
<Dir>out</Dir>
<Bits>1</Bits>
<Attribute>control</Attribute>
</RtlPorts>
<RtlPorts>
<name>data_9_q0</name>
<Object>data_9</Object>
<Type>array</Type>
<Scope></Scope>
<IOProtocol>ap_memory</IOProtocol>
<IOConfig></IOConfig>
<Dir>in</Dir>
<Bits>16</Bits>
<Attribute>data</Attribute>
</RtlPorts>
<RtlPorts>
<name>data_10_address0</name>
<Object>data_10</Object>
<Type>array</Type>
<Scope></Scope>
<IOProtocol>ap_memory</IOProtocol>
<IOConfig></IOConfig>
<Dir>out</Dir>
<Bits>7</Bits>
<Attribute>address</Attribute>
</RtlPorts>
<RtlPorts>
<name>data_10_ce0</name>
<Object>data_10</Object>
<Type>array</Type>
<Scope></Scope>
<IOProtocol>ap_memory</IOProtocol>
<IOConfig></IOConfig>
<Dir>out</Dir>
<Bits>1</Bits>
<Attribute>control</Attribute>
</RtlPorts>
<RtlPorts>
<name>data_10_q0</name>
<Object>data_10</Object>
<Type>array</Type>
<Scope></Scope>
<IOProtocol>ap_memory</IOProtocol>
<IOConfig></IOConfig>
<Dir>in</Dir>
<Bits>16</Bits>
<Attribute>data</Attribute>
</RtlPorts>
<RtlPorts>
<name>data_11_address0</name>
<Object>data_11</Object>
<Type>array</Type>
<Scope></Scope>
<IOProtocol>ap_memory</IOProtocol>
<IOConfig></IOConfig>
<Dir>out</Dir>
<Bits>7</Bits>
<Attribute>address</Attribute>
</RtlPorts>
<RtlPorts>
<name>data_11_ce0</name>
<Object>data_11</Object>
<Type>array</Type>
<Scope></Scope>
<IOProtocol>ap_memory</IOProtocol>
<IOConfig></IOConfig>
<Dir>out</Dir>
<Bits>1</Bits>
<Attribute>control</Attribute>
</RtlPorts>
<RtlPorts>
<name>data_11_q0</name>
<Object>data_11</Object>
<Type>array</Type>
<Scope></Scope>
<IOProtocol>ap_memory</IOProtocol>
<IOConfig></IOConfig>
<Dir>in</Dir>
<Bits>16</Bits>
<Attribute>data</Attribute>
</RtlPorts>
<RtlPorts>
<name>data_12_address0</name>
<Object>data_12</Object>
<Type>array</Type>
<Scope></Scope>
<IOProtocol>ap_memory</IOProtocol>
<IOConfig></IOConfig>
<Dir>out</Dir>
<Bits>7</Bits>
<Attribute>address</Attribute>
</RtlPorts>
<RtlPorts>
<name>data_12_ce0</name>
<Object>data_12</Object>
<Type>array</Type>
<Scope></Scope>
<IOProtocol>ap_memory</IOProtocol>
<IOConfig></IOConfig>
<Dir>out</Dir>
<Bits>1</Bits>
<Attribute>control</Attribute>
</RtlPorts>
<RtlPorts>
<name>data_12_q0</name>
<Object>data_12</Object>
<Type>array</Type>
<Scope></Scope>
<IOProtocol>ap_memory</IOProtocol>
<IOConfig></IOConfig>
<Dir>in</Dir>
<Bits>16</Bits>
<Attribute>data</Attribute>
</RtlPorts>
<RtlPorts>
<name>data_13_address0</name>
<Object>data_13</Object>
<Type>array</Type>
<Scope></Scope>
<IOProtocol>ap_memory</IOProtocol>
<IOConfig></IOConfig>
<Dir>out</Dir>
<Bits>7</Bits>
<Attribute>address</Attribute>
</RtlPorts>
<RtlPorts>
<name>data_13_ce0</name>
<Object>data_13</Object>
<Type>array</Type>
<Scope></Scope>
<IOProtocol>ap_memory</IOProtocol>
<IOConfig></IOConfig>
<Dir>out</Dir>
<Bits>1</Bits>
<Attribute>control</Attribute>
</RtlPorts>
<RtlPorts>
<name>data_13_q0</name>
<Object>data_13</Object>
<Type>array</Type>
<Scope></Scope>
<IOProtocol>ap_memory</IOProtocol>
<IOConfig></IOConfig>
<Dir>in</Dir>
<Bits>16</Bits>
<Attribute>data</Attribute>
</RtlPorts>
<RtlPorts>
<name>data_14_address0</name>
<Object>data_14</Object>
<Type>array</Type>
<Scope></Scope>
<IOProtocol>ap_memory</IOProtocol>
<IOConfig></IOConfig>
<Dir>out</Dir>
<Bits>7</Bits>
<Attribute>address</Attribute>
</RtlPorts>
<RtlPorts>
<name>data_14_ce0</name>
<Object>data_14</Object>
<Type>array</Type>
<Scope></Scope>
<IOProtocol>ap_memory</IOProtocol>
<IOConfig></IOConfig>
<Dir>out</Dir>
<Bits>1</Bits>
<Attribute>control</Attribute>
</RtlPorts>
<RtlPorts>
<name>data_14_q0</name>
<Object>data_14</Object>
<Type>array</Type>
<Scope></Scope>
<IOProtocol>ap_memory</IOProtocol>
<IOConfig></IOConfig>
<Dir>in</Dir>
<Bits>16</Bits>
<Attribute>data</Attribute>
</RtlPorts>
<RtlPorts>
<name>data_15_address0</name>
<Object>data_15</Object>
<Type>array</Type>
<Scope></Scope>
<IOProtocol>ap_memory</IOProtocol>
<IOConfig></IOConfig>
<Dir>out</Dir>
<Bits>7</Bits>
<Attribute>address</Attribute>
</RtlPorts>
<RtlPorts>
<name>data_15_ce0</name>
<Object>data_15</Object>
<Type>array</Type>
<Scope></Scope>
<IOProtocol>ap_memory</IOProtocol>
<IOConfig></IOConfig>
<Dir>out</Dir>
<Bits>1</Bits>
<Attribute>control</Attribute>
</RtlPorts>
<RtlPorts>
<name>data_15_q0</name>
<Object>data_15</Object>
<Type>array</Type>
<Scope></Scope>
<IOProtocol>ap_memory</IOProtocol>
<IOConfig></IOConfig>
<Dir>in</Dir>
<Bits>16</Bits>
<Attribute>data</Attribute>
</RtlPorts>
<RtlPorts>
<name>data_16_address0</name>
<Object>data_16</Object>
<Type>array</Type>
<Scope></Scope>
<IOProtocol>ap_memory</IOProtocol>
<IOConfig></IOConfig>
<Dir>out</Dir>
<Bits>7</Bits>
<Attribute>address</Attribute>
</RtlPorts>
<RtlPorts>
<name>data_16_ce0</name>
<Object>data_16</Object>
<Type>array</Type>
<Scope></Scope>
<IOProtocol>ap_memory</IOProtocol>
<IOConfig></IOConfig>
<Dir>out</Dir>
<Bits>1</Bits>
<Attribute>control</Attribute>
</RtlPorts>
<RtlPorts>
<name>data_16_q0</name>
<Object>data_16</Object>
<Type>array</Type>
<Scope></Scope>
<IOProtocol>ap_memory</IOProtocol>
<IOConfig></IOConfig>
<Dir>in</Dir>
<Bits>16</Bits>
<Attribute>data</Attribute>
</RtlPorts>
<RtlPorts>
<name>data_17_address0</name>
<Object>data_17</Object>
<Type>array</Type>
<Scope></Scope>
<IOProtocol>ap_memory</IOProtocol>
<IOConfig></IOConfig>
<Dir>out</Dir>
<Bits>7</Bits>
<Attribute>address</Attribute>
</RtlPorts>
<RtlPorts>
<name>data_17_ce0</name>
<Object>data_17</Object>
<Type>array</Type>
<Scope></Scope>
<IOProtocol>ap_memory</IOProtocol>
<IOConfig></IOConfig>
<Dir>out</Dir>
<Bits>1</Bits>
<Attribute>control</Attribute>
</RtlPorts>
<RtlPorts>
<name>data_17_q0</name>
<Object>data_17</Object>
<Type>array</Type>
<Scope></Scope>
<IOProtocol>ap_memory</IOProtocol>
<IOConfig></IOConfig>
<Dir>in</Dir>
<Bits>16</Bits>
<Attribute>data</Attribute>
</RtlPorts>
<RtlPorts>
<name>data_18_address0</name>
<Object>data_18</Object>
<Type>array</Type>
<Scope></Scope>
<IOProtocol>ap_memory</IOProtocol>
<IOConfig></IOConfig>
<Dir>out</Dir>
<Bits>7</Bits>
<Attribute>address</Attribute>
</RtlPorts>
<RtlPorts>
<name>data_18_ce0</name>
<Object>data_18</Object>
<Type>array</Type>
<Scope></Scope>
<IOProtocol>ap_memory</IOProtocol>
<IOConfig></IOConfig>
<Dir>out</Dir>
<Bits>1</Bits>
<Attribute>control</Attribute>
</RtlPorts>
<RtlPorts>
<name>data_18_q0</name>
<Object>data_18</Object>
<Type>array</Type>
<Scope></Scope>
<IOProtocol>ap_memory</IOProtocol>
<IOConfig></IOConfig>
<Dir>in</Dir>
<Bits>16</Bits>
<Attribute>data</Attribute>
</RtlPorts>
<RtlPorts>
<name>data_19_address0</name>
<Object>data_19</Object>
<Type>array</Type>
<Scope></Scope>
<IOProtocol>ap_memory</IOProtocol>
<IOConfig></IOConfig>
<Dir>out</Dir>
<Bits>7</Bits>
<Attribute>address</Attribute>
</RtlPorts>
<RtlPorts>
<name>data_19_ce0</name>
<Object>data_19</Object>
<Type>array</Type>
<Scope></Scope>
<IOProtocol>ap_memory</IOProtocol>
<IOConfig></IOConfig>
<Dir>out</Dir>
<Bits>1</Bits>
<Attribute>control</Attribute>
</RtlPorts>
<RtlPorts>
<name>data_19_q0</name>
<Object>data_19</Object>
<Type>array</Type>
<Scope></Scope>
<IOProtocol>ap_memory</IOProtocol>
<IOConfig></IOConfig>
<Dir>in</Dir>
<Bits>16</Bits>
<Attribute>data</Attribute>
</RtlPorts>
<RtlPorts>
<name>data_20_address0</name>
<Object>data_20</Object>
<Type>array</Type>
<Scope></Scope>
<IOProtocol>ap_memory</IOProtocol>
<IOConfig></IOConfig>
<Dir>out</Dir>
<Bits>7</Bits>
<Attribute>address</Attribute>
</RtlPorts>
<RtlPorts>
<name>data_20_ce0</name>
<Object>data_20</Object>
<Type>array</Type>
<Scope></Scope>
<IOProtocol>ap_memory</IOProtocol>
<IOConfig></IOConfig>
<Dir>out</Dir>
<Bits>1</Bits>
<Attribute>control</Attribute>
</RtlPorts>
<RtlPorts>
<name>data_20_q0</name>
<Object>data_20</Object>
<Type>array</Type>
<Scope></Scope>
<IOProtocol>ap_memory</IOProtocol>
<IOConfig></IOConfig>
<Dir>in</Dir>
<Bits>16</Bits>
<Attribute>data</Attribute>
</RtlPorts>
<RtlPorts>
<name>data_21_address0</name>
<Object>data_21</Object>
<Type>array</Type>
<Scope></Scope>
<IOProtocol>ap_memory</IOProtocol>
<IOConfig></IOConfig>
<Dir>out</Dir>
<Bits>7</Bits>
<Attribute>address</Attribute>
</RtlPorts>
<RtlPorts>
<name>data_21_ce0</name>
<Object>data_21</Object>
<Type>array</Type>
<Scope></Scope>
<IOProtocol>ap_memory</IOProtocol>
<IOConfig></IOConfig>
<Dir>out</Dir>
<Bits>1</Bits>
<Attribute>control</Attribute>
</RtlPorts>
<RtlPorts>
<name>data_21_q0</name>
<Object>data_21</Object>
<Type>array</Type>
<Scope></Scope>
<IOProtocol>ap_memory</IOProtocol>
<IOConfig></IOConfig>
<Dir>in</Dir>
<Bits>16</Bits>
<Attribute>data</Attribute>
</RtlPorts>
<RtlPorts>
<name>data_22_address0</name>
<Object>data_22</Object>
<Type>array</Type>
<Scope></Scope>
<IOProtocol>ap_memory</IOProtocol>
<IOConfig></IOConfig>
<Dir>out</Dir>
<Bits>7</Bits>
<Attribute>address</Attribute>
</RtlPorts>
<RtlPorts>
<name>data_22_ce0</name>
<Object>data_22</Object>
<Type>array</Type>
<Scope></Scope>
<IOProtocol>ap_memory</IOProtocol>
<IOConfig></IOConfig>
<Dir>out</Dir>
<Bits>1</Bits>
<Attribute>control</Attribute>
</RtlPorts>
<RtlPorts>
<name>data_22_q0</name>
<Object>data_22</Object>
<Type>array</Type>
<Scope></Scope>
<IOProtocol>ap_memory</IOProtocol>
<IOConfig></IOConfig>
<Dir>in</Dir>
<Bits>16</Bits>
<Attribute>data</Attribute>
</RtlPorts>
<RtlPorts>
<name>data_23_address0</name>
<Object>data_23</Object>
<Type>array</Type>
<Scope></Scope>
<IOProtocol>ap_memory</IOProtocol>
<IOConfig></IOConfig>
<Dir>out</Dir>
<Bits>7</Bits>
<Attribute>address</Attribute>
</RtlPorts>
<RtlPorts>
<name>data_23_ce0</name>
<Object>data_23</Object>
<Type>array</Type>
<Scope></Scope>
<IOProtocol>ap_memory</IOProtocol>
<IOConfig></IOConfig>
<Dir>out</Dir>
<Bits>1</Bits>
<Attribute>control</Attribute>
</RtlPorts>
<RtlPorts>
<name>data_23_q0</name>
<Object>data_23</Object>
<Type>array</Type>
<Scope></Scope>
<IOProtocol>ap_memory</IOProtocol>
<IOConfig></IOConfig>
<Dir>in</Dir>
<Bits>16</Bits>
<Attribute>data</Attribute>
</RtlPorts>
<RtlPorts>
<name>data_24_address0</name>
<Object>data_24</Object>
<Type>array</Type>
<Scope></Scope>
<IOProtocol>ap_memory</IOProtocol>
<IOConfig></IOConfig>
<Dir>out</Dir>
<Bits>7</Bits>
<Attribute>address</Attribute>
</RtlPorts>
<RtlPorts>
<name>data_24_ce0</name>
<Object>data_24</Object>
<Type>array</Type>
<Scope></Scope>
<IOProtocol>ap_memory</IOProtocol>
<IOConfig></IOConfig>
<Dir>out</Dir>
<Bits>1</Bits>
<Attribute>control</Attribute>
</RtlPorts>
<RtlPorts>
<name>data_24_q0</name>
<Object>data_24</Object>
<Type>array</Type>
<Scope></Scope>
<IOProtocol>ap_memory</IOProtocol>
<IOConfig></IOConfig>
<Dir>in</Dir>
<Bits>16</Bits>
<Attribute>data</Attribute>
</RtlPorts>
<RtlPorts>
<name>data_25_address0</name>
<Object>data_25</Object>
<Type>array</Type>
<Scope></Scope>
<IOProtocol>ap_memory</IOProtocol>
<IOConfig></IOConfig>
<Dir>out</Dir>
<Bits>7</Bits>
<Attribute>address</Attribute>
</RtlPorts>
<RtlPorts>
<name>data_25_ce0</name>
<Object>data_25</Object>
<Type>array</Type>
<Scope></Scope>
<IOProtocol>ap_memory</IOProtocol>
<IOConfig></IOConfig>
<Dir>out</Dir>
<Bits>1</Bits>
<Attribute>control</Attribute>
</RtlPorts>
<RtlPorts>
<name>data_25_q0</name>
<Object>data_25</Object>
<Type>array</Type>
<Scope></Scope>
<IOProtocol>ap_memory</IOProtocol>
<IOConfig></IOConfig>
<Dir>in</Dir>
<Bits>16</Bits>
<Attribute>data</Attribute>
</RtlPorts>
<RtlPorts>
<name>data_26_address0</name>
<Object>data_26</Object>
<Type>array</Type>
<Scope></Scope>
<IOProtocol>ap_memory</IOProtocol>
<IOConfig></IOConfig>
<Dir>out</Dir>
<Bits>7</Bits>
<Attribute>address</Attribute>
</RtlPorts>
<RtlPorts>
<name>data_26_ce0</name>
<Object>data_26</Object>
<Type>array</Type>
<Scope></Scope>
<IOProtocol>ap_memory</IOProtocol>
<IOConfig></IOConfig>
<Dir>out</Dir>
<Bits>1</Bits>
<Attribute>control</Attribute>
</RtlPorts>
<RtlPorts>
<name>data_26_q0</name>
<Object>data_26</Object>
<Type>array</Type>
<Scope></Scope>
<IOProtocol>ap_memory</IOProtocol>
<IOConfig></IOConfig>
<Dir>in</Dir>
<Bits>16</Bits>
<Attribute>data</Attribute>
</RtlPorts>
<RtlPorts>
<name>data_27_address0</name>
<Object>data_27</Object>
<Type>array</Type>
<Scope></Scope>
<IOProtocol>ap_memory</IOProtocol>
<IOConfig></IOConfig>
<Dir>out</Dir>
<Bits>7</Bits>
<Attribute>address</Attribute>
</RtlPorts>
<RtlPorts>
<name>data_27_ce0</name>
<Object>data_27</Object>
<Type>array</Type>
<Scope></Scope>
<IOProtocol>ap_memory</IOProtocol>
<IOConfig></IOConfig>
<Dir>out</Dir>
<Bits>1</Bits>
<Attribute>control</Attribute>
</RtlPorts>
<RtlPorts>
<name>data_27_q0</name>
<Object>data_27</Object>
<Type>array</Type>
<Scope></Scope>
<IOProtocol>ap_memory</IOProtocol>
<IOConfig></IOConfig>
<Dir>in</Dir>
<Bits>16</Bits>
<Attribute>data</Attribute>
</RtlPorts>
<RtlPorts>
<name>data_28_address0</name>
<Object>data_28</Object>
<Type>array</Type>
<Scope></Scope>
<IOProtocol>ap_memory</IOProtocol>
<IOConfig></IOConfig>
<Dir>out</Dir>
<Bits>7</Bits>
<Attribute>address</Attribute>
</RtlPorts>
<RtlPorts>
<name>data_28_ce0</name>
<Object>data_28</Object>
<Type>array</Type>
<Scope></Scope>
<IOProtocol>ap_memory</IOProtocol>
<IOConfig></IOConfig>
<Dir>out</Dir>
<Bits>1</Bits>
<Attribute>control</Attribute>
</RtlPorts>
<RtlPorts>
<name>data_28_q0</name>
<Object>data_28</Object>
<Type>array</Type>
<Scope></Scope>
<IOProtocol>ap_memory</IOProtocol>
<IOConfig></IOConfig>
<Dir>in</Dir>
<Bits>16</Bits>
<Attribute>data</Attribute>
</RtlPorts>
<RtlPorts>
<name>data_29_address0</name>
<Object>data_29</Object>
<Type>array</Type>
<Scope></Scope>
<IOProtocol>ap_memory</IOProtocol>
<IOConfig></IOConfig>
<Dir>out</Dir>
<Bits>7</Bits>
<Attribute>address</Attribute>
</RtlPorts>
<RtlPorts>
<name>data_29_ce0</name>
<Object>data_29</Object>
<Type>array</Type>
<Scope></Scope>
<IOProtocol>ap_memory</IOProtocol>
<IOConfig></IOConfig>
<Dir>out</Dir>
<Bits>1</Bits>
<Attribute>control</Attribute>
</RtlPorts>
<RtlPorts>
<name>data_29_q0</name>
<Object>data_29</Object>
<Type>array</Type>
<Scope></Scope>
<IOProtocol>ap_memory</IOProtocol>
<IOConfig></IOConfig>
<Dir>in</Dir>
<Bits>16</Bits>
<Attribute>data</Attribute>
</RtlPorts>
<RtlPorts>
<name>data_30_address0</name>
<Object>data_30</Object>
<Type>array</Type>
<Scope></Scope>
<IOProtocol>ap_memory</IOProtocol>
<IOConfig></IOConfig>
<Dir>out</Dir>
<Bits>7</Bits>
<Attribute>address</Attribute>
</RtlPorts>
<RtlPorts>
<name>data_30_ce0</name>
<Object>data_30</Object>
<Type>array</Type>
<Scope></Scope>
<IOProtocol>ap_memory</IOProtocol>
<IOConfig></IOConfig>
<Dir>out</Dir>
<Bits>1</Bits>
<Attribute>control</Attribute>
</RtlPorts>
<RtlPorts>
<name>data_30_q0</name>
<Object>data_30</Object>
<Type>array</Type>
<Scope></Scope>
<IOProtocol>ap_memory</IOProtocol>
<IOConfig></IOConfig>
<Dir>in</Dir>
<Bits>16</Bits>
<Attribute>data</Attribute>
</RtlPorts>
<RtlPorts>
<name>data_31_address0</name>
<Object>data_31</Object>
<Type>array</Type>
<Scope></Scope>
<IOProtocol>ap_memory</IOProtocol>
<IOConfig></IOConfig>
<Dir>out</Dir>
<Bits>7</Bits>
<Attribute>address</Attribute>
</RtlPorts>
<RtlPorts>
<name>data_31_ce0</name>
<Object>data_31</Object>
<Type>array</Type>
<Scope></Scope>
<IOProtocol>ap_memory</IOProtocol>
<IOConfig></IOConfig>
<Dir>out</Dir>
<Bits>1</Bits>
<Attribute>control</Attribute>
</RtlPorts>
<RtlPorts>
<name>data_31_q0</name>
<Object>data_31</Object>
<Type>array</Type>
<Scope></Scope>
<IOProtocol>ap_memory</IOProtocol>
<IOConfig></IOConfig>
<Dir>in</Dir>
<Bits>16</Bits>
<Attribute>data</Attribute>
</RtlPorts>
<RtlPorts>
<name>data_32_address0</name>
<Object>data_32</Object>
<Type>array</Type>
<Scope></Scope>
<IOProtocol>ap_memory</IOProtocol>
<IOConfig></IOConfig>
<Dir>out</Dir>
<Bits>7</Bits>
<Attribute>address</Attribute>
</RtlPorts>
<RtlPorts>
<name>data_32_ce0</name>
<Object>data_32</Object>
<Type>array</Type>
<Scope></Scope>
<IOProtocol>ap_memory</IOProtocol>
<IOConfig></IOConfig>
<Dir>out</Dir>
<Bits>1</Bits>
<Attribute>control</Attribute>
</RtlPorts>
<RtlPorts>
<name>data_32_q0</name>
<Object>data_32</Object>
<Type>array</Type>
<Scope></Scope>
<IOProtocol>ap_memory</IOProtocol>
<IOConfig></IOConfig>
<Dir>in</Dir>
<Bits>16</Bits>
<Attribute>data</Attribute>
</RtlPorts>
<RtlPorts>
<name>data_33_address0</name>
<Object>data_33</Object>
<Type>array</Type>
<Scope></Scope>
<IOProtocol>ap_memory</IOProtocol>
<IOConfig></IOConfig>
<Dir>out</Dir>
<Bits>7</Bits>
<Attribute>address</Attribute>
</RtlPorts>
<RtlPorts>
<name>data_33_ce0</name>
<Object>data_33</Object>
<Type>array</Type>
<Scope></Scope>
<IOProtocol>ap_memory</IOProtocol>
<IOConfig></IOConfig>
<Dir>out</Dir>
<Bits>1</Bits>
<Attribute>control</Attribute>
</RtlPorts>
<RtlPorts>
<name>data_33_q0</name>
<Object>data_33</Object>
<Type>array</Type>
<Scope></Scope>
<IOProtocol>ap_memory</IOProtocol>
<IOConfig></IOConfig>
<Dir>in</Dir>
<Bits>16</Bits>
<Attribute>data</Attribute>
</RtlPorts>
<RtlPorts>
<name>data_34_address0</name>
<Object>data_34</Object>
<Type>array</Type>
<Scope></Scope>
<IOProtocol>ap_memory</IOProtocol>
<IOConfig></IOConfig>
<Dir>out</Dir>
<Bits>7</Bits>
<Attribute>address</Attribute>
</RtlPorts>
<RtlPorts>
<name>data_34_ce0</name>
<Object>data_34</Object>
<Type>array</Type>
<Scope></Scope>
<IOProtocol>ap_memory</IOProtocol>
<IOConfig></IOConfig>
<Dir>out</Dir>
<Bits>1</Bits>
<Attribute>control</Attribute>
</RtlPorts>
<RtlPorts>
<name>data_34_q0</name>
<Object>data_34</Object>
<Type>array</Type>
<Scope></Scope>
<IOProtocol>ap_memory</IOProtocol>
<IOConfig></IOConfig>
<Dir>in</Dir>
<Bits>16</Bits>
<Attribute>data</Attribute>
</RtlPorts>
<RtlPorts>
<name>data_35_address0</name>
<Object>data_35</Object>
<Type>array</Type>
<Scope></Scope>
<IOProtocol>ap_memory</IOProtocol>
<IOConfig></IOConfig>
<Dir>out</Dir>
<Bits>7</Bits>
<Attribute>address</Attribute>
</RtlPorts>
<RtlPorts>
<name>data_35_ce0</name>
<Object>data_35</Object>
<Type>array</Type>
<Scope></Scope>
<IOProtocol>ap_memory</IOProtocol>
<IOConfig></IOConfig>
<Dir>out</Dir>
<Bits>1</Bits>
<Attribute>control</Attribute>
</RtlPorts>
<RtlPorts>
<name>data_35_q0</name>
<Object>data_35</Object>
<Type>array</Type>
<Scope></Scope>
<IOProtocol>ap_memory</IOProtocol>
<IOConfig></IOConfig>
<Dir>in</Dir>
<Bits>16</Bits>
<Attribute>data</Attribute>
</RtlPorts>
<RtlPorts>
<name>data_36_address0</name>
<Object>data_36</Object>
<Type>array</Type>
<Scope></Scope>
<IOProtocol>ap_memory</IOProtocol>
<IOConfig></IOConfig>
<Dir>out</Dir>
<Bits>7</Bits>
<Attribute>address</Attribute>
</RtlPorts>
<RtlPorts>
<name>data_36_ce0</name>
<Object>data_36</Object>
<Type>array</Type>
<Scope></Scope>
<IOProtocol>ap_memory</IOProtocol>
<IOConfig></IOConfig>
<Dir>out</Dir>
<Bits>1</Bits>
<Attribute>control</Attribute>
</RtlPorts>
<RtlPorts>
<name>data_36_q0</name>
<Object>data_36</Object>
<Type>array</Type>
<Scope></Scope>
<IOProtocol>ap_memory</IOProtocol>
<IOConfig></IOConfig>
<Dir>in</Dir>
<Bits>16</Bits>
<Attribute>data</Attribute>
</RtlPorts>
<RtlPorts>
<name>data_37_address0</name>
<Object>data_37</Object>
<Type>array</Type>
<Scope></Scope>
<IOProtocol>ap_memory</IOProtocol>
<IOConfig></IOConfig>
<Dir>out</Dir>
<Bits>7</Bits>
<Attribute>address</Attribute>
</RtlPorts>
<RtlPorts>
<name>data_37_ce0</name>
<Object>data_37</Object>
<Type>array</Type>
<Scope></Scope>
<IOProtocol>ap_memory</IOProtocol>
<IOConfig></IOConfig>
<Dir>out</Dir>
<Bits>1</Bits>
<Attribute>control</Attribute>
</RtlPorts>
<RtlPorts>
<name>data_37_q0</name>
<Object>data_37</Object>
<Type>array</Type>
<Scope></Scope>
<IOProtocol>ap_memory</IOProtocol>
<IOConfig></IOConfig>
<Dir>in</Dir>
<Bits>16</Bits>
<Attribute>data</Attribute>
</RtlPorts>
<RtlPorts>
<name>data_38_address0</name>
<Object>data_38</Object>
<Type>array</Type>
<Scope></Scope>
<IOProtocol>ap_memory</IOProtocol>
<IOConfig></IOConfig>
<Dir>out</Dir>
<Bits>7</Bits>
<Attribute>address</Attribute>
</RtlPorts>
<RtlPorts>
<name>data_38_ce0</name>
<Object>data_38</Object>
<Type>array</Type>
<Scope></Scope>
<IOProtocol>ap_memory</IOProtocol>
<IOConfig></IOConfig>
<Dir>out</Dir>
<Bits>1</Bits>
<Attribute>control</Attribute>
</RtlPorts>
<RtlPorts>
<name>data_38_q0</name>
<Object>data_38</Object>
<Type>array</Type>
<Scope></Scope>
<IOProtocol>ap_memory</IOProtocol>
<IOConfig></IOConfig>
<Dir>in</Dir>
<Bits>16</Bits>
<Attribute>data</Attribute>
</RtlPorts>
<RtlPorts>
<name>data_39_address0</name>
<Object>data_39</Object>
<Type>array</Type>
<Scope></Scope>
<IOProtocol>ap_memory</IOProtocol>
<IOConfig></IOConfig>
<Dir>out</Dir>
<Bits>7</Bits>
<Attribute>address</Attribute>
</RtlPorts>
<RtlPorts>
<name>data_39_ce0</name>
<Object>data_39</Object>
<Type>array</Type>
<Scope></Scope>
<IOProtocol>ap_memory</IOProtocol>
<IOConfig></IOConfig>
<Dir>out</Dir>
<Bits>1</Bits>
<Attribute>control</Attribute>
</RtlPorts>
<RtlPorts>
<name>data_39_q0</name>
<Object>data_39</Object>
<Type>array</Type>
<Scope></Scope>
<IOProtocol>ap_memory</IOProtocol>
<IOConfig></IOConfig>
<Dir>in</Dir>
<Bits>16</Bits>
<Attribute>data</Attribute>
</RtlPorts>
<RtlPorts>
<name>data_40_address0</name>
<Object>data_40</Object>
<Type>array</Type>
<Scope></Scope>
<IOProtocol>ap_memory</IOProtocol>
<IOConfig></IOConfig>
<Dir>out</Dir>
<Bits>7</Bits>
<Attribute>address</Attribute>
</RtlPorts>
<RtlPorts>
<name>data_40_ce0</name>
<Object>data_40</Object>
<Type>array</Type>
<Scope></Scope>
<IOProtocol>ap_memory</IOProtocol>
<IOConfig></IOConfig>
<Dir>out</Dir>
<Bits>1</Bits>
<Attribute>control</Attribute>
</RtlPorts>
<RtlPorts>
<name>data_40_q0</name>
<Object>data_40</Object>
<Type>array</Type>
<Scope></Scope>
<IOProtocol>ap_memory</IOProtocol>
<IOConfig></IOConfig>
<Dir>in</Dir>
<Bits>16</Bits>
<Attribute>data</Attribute>
</RtlPorts>
<RtlPorts>
<name>data_41_address0</name>
<Object>data_41</Object>
<Type>array</Type>
<Scope></Scope>
<IOProtocol>ap_memory</IOProtocol>
<IOConfig></IOConfig>
<Dir>out</Dir>
<Bits>7</Bits>
<Attribute>address</Attribute>
</RtlPorts>
<RtlPorts>
<name>data_41_ce0</name>
<Object>data_41</Object>
<Type>array</Type>
<Scope></Scope>
<IOProtocol>ap_memory</IOProtocol>
<IOConfig></IOConfig>
<Dir>out</Dir>
<Bits>1</Bits>
<Attribute>control</Attribute>
</RtlPorts>
<RtlPorts>
<name>data_41_q0</name>
<Object>data_41</Object>
<Type>array</Type>
<Scope></Scope>
<IOProtocol>ap_memory</IOProtocol>
<IOConfig></IOConfig>
<Dir>in</Dir>
<Bits>16</Bits>
<Attribute>data</Attribute>
</RtlPorts>
<RtlPorts>
<name>data_42_address0</name>
<Object>data_42</Object>
<Type>array</Type>
<Scope></Scope>
<IOProtocol>ap_memory</IOProtocol>
<IOConfig></IOConfig>
<Dir>out</Dir>
<Bits>7</Bits>
<Attribute>address</Attribute>
</RtlPorts>
<RtlPorts>
<name>data_42_ce0</name>
<Object>data_42</Object>
<Type>array</Type>
<Scope></Scope>
<IOProtocol>ap_memory</IOProtocol>
<IOConfig></IOConfig>
<Dir>out</Dir>
<Bits>1</Bits>
<Attribute>control</Attribute>
</RtlPorts>
<RtlPorts>
<name>data_42_q0</name>
<Object>data_42</Object>
<Type>array</Type>
<Scope></Scope>
<IOProtocol>ap_memory</IOProtocol>
<IOConfig></IOConfig>
<Dir>in</Dir>
<Bits>16</Bits>
<Attribute>data</Attribute>
</RtlPorts>
<RtlPorts>
<name>data_43_address0</name>
<Object>data_43</Object>
<Type>array</Type>
<Scope></Scope>
<IOProtocol>ap_memory</IOProtocol>
<IOConfig></IOConfig>
<Dir>out</Dir>
<Bits>7</Bits>
<Attribute>address</Attribute>
</RtlPorts>
<RtlPorts>
<name>data_43_ce0</name>
<Object>data_43</Object>
<Type>array</Type>
<Scope></Scope>
<IOProtocol>ap_memory</IOProtocol>
<IOConfig></IOConfig>
<Dir>out</Dir>
<Bits>1</Bits>
<Attribute>control</Attribute>
</RtlPorts>
<RtlPorts>
<name>data_43_q0</name>
<Object>data_43</Object>
<Type>array</Type>
<Scope></Scope>
<IOProtocol>ap_memory</IOProtocol>
<IOConfig></IOConfig>
<Dir>in</Dir>
<Bits>16</Bits>
<Attribute>data</Attribute>
</RtlPorts>
<RtlPorts>
<name>data_44_address0</name>
<Object>data_44</Object>
<Type>array</Type>
<Scope></Scope>
<IOProtocol>ap_memory</IOProtocol>
<IOConfig></IOConfig>
<Dir>out</Dir>
<Bits>7</Bits>
<Attribute>address</Attribute>
</RtlPorts>
<RtlPorts>
<name>data_44_ce0</name>
<Object>data_44</Object>
<Type>array</Type>
<Scope></Scope>
<IOProtocol>ap_memory</IOProtocol>
<IOConfig></IOConfig>
<Dir>out</Dir>
<Bits>1</Bits>
<Attribute>control</Attribute>
</RtlPorts>
<RtlPorts>
<name>data_44_q0</name>
<Object>data_44</Object>
<Type>array</Type>
<Scope></Scope>
<IOProtocol>ap_memory</IOProtocol>
<IOConfig></IOConfig>
<Dir>in</Dir>
<Bits>16</Bits>
<Attribute>data</Attribute>
</RtlPorts>
<RtlPorts>
<name>data_45_address0</name>
<Object>data_45</Object>
<Type>array</Type>
<Scope></Scope>
<IOProtocol>ap_memory</IOProtocol>
<IOConfig></IOConfig>
<Dir>out</Dir>
<Bits>7</Bits>
<Attribute>address</Attribute>
</RtlPorts>
<RtlPorts>
<name>data_45_ce0</name>
<Object>data_45</Object>
<Type>array</Type>
<Scope></Scope>
<IOProtocol>ap_memory</IOProtocol>
<IOConfig></IOConfig>
<Dir>out</Dir>
<Bits>1</Bits>
<Attribute>control</Attribute>
</RtlPorts>
<RtlPorts>
<name>data_45_q0</name>
<Object>data_45</Object>
<Type>array</Type>
<Scope></Scope>
<IOProtocol>ap_memory</IOProtocol>
<IOConfig></IOConfig>
<Dir>in</Dir>
<Bits>16</Bits>
<Attribute>data</Attribute>
</RtlPorts>
<RtlPorts>
<name>data_46_address0</name>
<Object>data_46</Object>
<Type>array</Type>
<Scope></Scope>
<IOProtocol>ap_memory</IOProtocol>
<IOConfig></IOConfig>
<Dir>out</Dir>
<Bits>7</Bits>
<Attribute>address</Attribute>
</RtlPorts>
<RtlPorts>
<name>data_46_ce0</name>
<Object>data_46</Object>
<Type>array</Type>
<Scope></Scope>
<IOProtocol>ap_memory</IOProtocol>
<IOConfig></IOConfig>
<Dir>out</Dir>
<Bits>1</Bits>
<Attribute>control</Attribute>
</RtlPorts>
<RtlPorts>
<name>data_46_q0</name>
<Object>data_46</Object>
<Type>array</Type>
<Scope></Scope>
<IOProtocol>ap_memory</IOProtocol>
<IOConfig></IOConfig>
<Dir>in</Dir>
<Bits>16</Bits>
<Attribute>data</Attribute>
</RtlPorts>
<RtlPorts>
<name>data_47_address0</name>
<Object>data_47</Object>
<Type>array</Type>
<Scope></Scope>
<IOProtocol>ap_memory</IOProtocol>
<IOConfig></IOConfig>
<Dir>out</Dir>
<Bits>7</Bits>
<Attribute>address</Attribute>
</RtlPorts>
<RtlPorts>
<name>data_47_ce0</name>
<Object>data_47</Object>
<Type>array</Type>
<Scope></Scope>
<IOProtocol>ap_memory</IOProtocol>
<IOConfig></IOConfig>
<Dir>out</Dir>
<Bits>1</Bits>
<Attribute>control</Attribute>
</RtlPorts>
<RtlPorts>
<name>data_47_q0</name>
<Object>data_47</Object>
<Type>array</Type>
<Scope></Scope>
<IOProtocol>ap_memory</IOProtocol>
<IOConfig></IOConfig>
<Dir>in</Dir>
<Bits>16</Bits>
<Attribute>data</Attribute>
</RtlPorts>
<RtlPorts>
<name>data_48_address0</name>
<Object>data_48</Object>
<Type>array</Type>
<Scope></Scope>
<IOProtocol>ap_memory</IOProtocol>
<IOConfig></IOConfig>
<Dir>out</Dir>
<Bits>7</Bits>
<Attribute>address</Attribute>
</RtlPorts>
<RtlPorts>
<name>data_48_ce0</name>
<Object>data_48</Object>
<Type>array</Type>
<Scope></Scope>
<IOProtocol>ap_memory</IOProtocol>
<IOConfig></IOConfig>
<Dir>out</Dir>
<Bits>1</Bits>
<Attribute>control</Attribute>
</RtlPorts>
<RtlPorts>
<name>data_48_q0</name>
<Object>data_48</Object>
<Type>array</Type>
<Scope></Scope>
<IOProtocol>ap_memory</IOProtocol>
<IOConfig></IOConfig>
<Dir>in</Dir>
<Bits>16</Bits>
<Attribute>data</Attribute>
</RtlPorts>
<RtlPorts>
<name>data_49_address0</name>
<Object>data_49</Object>
<Type>array</Type>
<Scope></Scope>
<IOProtocol>ap_memory</IOProtocol>
<IOConfig></IOConfig>
<Dir>out</Dir>
<Bits>7</Bits>
<Attribute>address</Attribute>
</RtlPorts>
<RtlPorts>
<name>data_49_ce0</name>
<Object>data_49</Object>
<Type>array</Type>
<Scope></Scope>
<IOProtocol>ap_memory</IOProtocol>
<IOConfig></IOConfig>
<Dir>out</Dir>
<Bits>1</Bits>
<Attribute>control</Attribute>
</RtlPorts>
<RtlPorts>
<name>data_49_q0</name>
<Object>data_49</Object>
<Type>array</Type>
<Scope></Scope>
<IOProtocol>ap_memory</IOProtocol>
<IOConfig></IOConfig>
<Dir>in</Dir>
<Bits>16</Bits>
<Attribute>data</Attribute>
</RtlPorts>
<RtlPorts>
<name>data_50_address0</name>
<Object>data_50</Object>
<Type>array</Type>
<Scope></Scope>
<IOProtocol>ap_memory</IOProtocol>
<IOConfig></IOConfig>
<Dir>out</Dir>
<Bits>7</Bits>
<Attribute>address</Attribute>
</RtlPorts>
<RtlPorts>
<name>data_50_ce0</name>
<Object>data_50</Object>
<Type>array</Type>
<Scope></Scope>
<IOProtocol>ap_memory</IOProtocol>
<IOConfig></IOConfig>
<Dir>out</Dir>
<Bits>1</Bits>
<Attribute>control</Attribute>
</RtlPorts>
<RtlPorts>
<name>data_50_q0</name>
<Object>data_50</Object>
<Type>array</Type>
<Scope></Scope>
<IOProtocol>ap_memory</IOProtocol>
<IOConfig></IOConfig>
<Dir>in</Dir>
<Bits>16</Bits>
<Attribute>data</Attribute>
</RtlPorts>
<RtlPorts>
<name>data_51_address0</name>
<Object>data_51</Object>
<Type>array</Type>
<Scope></Scope>
<IOProtocol>ap_memory</IOProtocol>
<IOConfig></IOConfig>
<Dir>out</Dir>
<Bits>7</Bits>
<Attribute>address</Attribute>
</RtlPorts>
<RtlPorts>
<name>data_51_ce0</name>
<Object>data_51</Object>
<Type>array</Type>
<Scope></Scope>
<IOProtocol>ap_memory</IOProtocol>
<IOConfig></IOConfig>
<Dir>out</Dir>
<Bits>1</Bits>
<Attribute>control</Attribute>
</RtlPorts>
<RtlPorts>
<name>data_51_q0</name>
<Object>data_51</Object>
<Type>array</Type>
<Scope></Scope>
<IOProtocol>ap_memory</IOProtocol>
<IOConfig></IOConfig>
<Dir>in</Dir>
<Bits>16</Bits>
<Attribute>data</Attribute>
</RtlPorts>
<RtlPorts>
<name>data_52_address0</name>
<Object>data_52</Object>
<Type>array</Type>
<Scope></Scope>
<IOProtocol>ap_memory</IOProtocol>
<IOConfig></IOConfig>
<Dir>out</Dir>
<Bits>7</Bits>
<Attribute>address</Attribute>
</RtlPorts>
<RtlPorts>
<name>data_52_ce0</name>
<Object>data_52</Object>
<Type>array</Type>
<Scope></Scope>
<IOProtocol>ap_memory</IOProtocol>
<IOConfig></IOConfig>
<Dir>out</Dir>
<Bits>1</Bits>
<Attribute>control</Attribute>
</RtlPorts>
<RtlPorts>
<name>data_52_q0</name>
<Object>data_52</Object>
<Type>array</Type>
<Scope></Scope>
<IOProtocol>ap_memory</IOProtocol>
<IOConfig></IOConfig>
<Dir>in</Dir>
<Bits>16</Bits>
<Attribute>data</Attribute>
</RtlPorts>
<RtlPorts>
<name>data_53_address0</name>
<Object>data_53</Object>
<Type>array</Type>
<Scope></Scope>
<IOProtocol>ap_memory</IOProtocol>
<IOConfig></IOConfig>
<Dir>out</Dir>
<Bits>7</Bits>
<Attribute>address</Attribute>
</RtlPorts>
<RtlPorts>
<name>data_53_ce0</name>
<Object>data_53</Object>
<Type>array</Type>
<Scope></Scope>
<IOProtocol>ap_memory</IOProtocol>
<IOConfig></IOConfig>
<Dir>out</Dir>
<Bits>1</Bits>
<Attribute>control</Attribute>
</RtlPorts>
<RtlPorts>
<name>data_53_q0</name>
<Object>data_53</Object>
<Type>array</Type>
<Scope></Scope>
<IOProtocol>ap_memory</IOProtocol>
<IOConfig></IOConfig>
<Dir>in</Dir>
<Bits>16</Bits>
<Attribute>data</Attribute>
</RtlPorts>
<RtlPorts>
<name>data_54_address0</name>
<Object>data_54</Object>
<Type>array</Type>
<Scope></Scope>
<IOProtocol>ap_memory</IOProtocol>
<IOConfig></IOConfig>
<Dir>out</Dir>
<Bits>7</Bits>
<Attribute>address</Attribute>
</RtlPorts>
<RtlPorts>
<name>data_54_ce0</name>
<Object>data_54</Object>
<Type>array</Type>
<Scope></Scope>
<IOProtocol>ap_memory</IOProtocol>
<IOConfig></IOConfig>
<Dir>out</Dir>
<Bits>1</Bits>
<Attribute>control</Attribute>
</RtlPorts>
<RtlPorts>
<name>data_54_q0</name>
<Object>data_54</Object>
<Type>array</Type>
<Scope></Scope>
<IOProtocol>ap_memory</IOProtocol>
<IOConfig></IOConfig>
<Dir>in</Dir>
<Bits>16</Bits>
<Attribute>data</Attribute>
</RtlPorts>
<RtlPorts>
<name>data_55_address0</name>
<Object>data_55</Object>
<Type>array</Type>
<Scope></Scope>
<IOProtocol>ap_memory</IOProtocol>
<IOConfig></IOConfig>
<Dir>out</Dir>
<Bits>7</Bits>
<Attribute>address</Attribute>
</RtlPorts>
<RtlPorts>
<name>data_55_ce0</name>
<Object>data_55</Object>
<Type>array</Type>
<Scope></Scope>
<IOProtocol>ap_memory</IOProtocol>
<IOConfig></IOConfig>
<Dir>out</Dir>
<Bits>1</Bits>
<Attribute>control</Attribute>
</RtlPorts>
<RtlPorts>
<name>data_55_q0</name>
<Object>data_55</Object>
<Type>array</Type>
<Scope></Scope>
<IOProtocol>ap_memory</IOProtocol>
<IOConfig></IOConfig>
<Dir>in</Dir>
<Bits>16</Bits>
<Attribute>data</Attribute>
</RtlPorts>
<RtlPorts>
<name>data_56_address0</name>
<Object>data_56</Object>
<Type>array</Type>
<Scope></Scope>
<IOProtocol>ap_memory</IOProtocol>
<IOConfig></IOConfig>
<Dir>out</Dir>
<Bits>7</Bits>
<Attribute>address</Attribute>
</RtlPorts>
<RtlPorts>
<name>data_56_ce0</name>
<Object>data_56</Object>
<Type>array</Type>
<Scope></Scope>
<IOProtocol>ap_memory</IOProtocol>
<IOConfig></IOConfig>
<Dir>out</Dir>
<Bits>1</Bits>
<Attribute>control</Attribute>
</RtlPorts>
<RtlPorts>
<name>data_56_q0</name>
<Object>data_56</Object>
<Type>array</Type>
<Scope></Scope>
<IOProtocol>ap_memory</IOProtocol>
<IOConfig></IOConfig>
<Dir>in</Dir>
<Bits>16</Bits>
<Attribute>data</Attribute>
</RtlPorts>
<RtlPorts>
<name>data_57_address0</name>
<Object>data_57</Object>
<Type>array</Type>
<Scope></Scope>
<IOProtocol>ap_memory</IOProtocol>
<IOConfig></IOConfig>
<Dir>out</Dir>
<Bits>7</Bits>
<Attribute>address</Attribute>
</RtlPorts>
<RtlPorts>
<name>data_57_ce0</name>
<Object>data_57</Object>
<Type>array</Type>
<Scope></Scope>
<IOProtocol>ap_memory</IOProtocol>
<IOConfig></IOConfig>
<Dir>out</Dir>
<Bits>1</Bits>
<Attribute>control</Attribute>
</RtlPorts>
<RtlPorts>
<name>data_57_q0</name>
<Object>data_57</Object>
<Type>array</Type>
<Scope></Scope>
<IOProtocol>ap_memory</IOProtocol>
<IOConfig></IOConfig>
<Dir>in</Dir>
<Bits>16</Bits>
<Attribute>data</Attribute>
</RtlPorts>
<RtlPorts>
<name>data_58_address0</name>
<Object>data_58</Object>
<Type>array</Type>
<Scope></Scope>
<IOProtocol>ap_memory</IOProtocol>
<IOConfig></IOConfig>
<Dir>out</Dir>
<Bits>7</Bits>
<Attribute>address</Attribute>
</RtlPorts>
<RtlPorts>
<name>data_58_ce0</name>
<Object>data_58</Object>
<Type>array</Type>
<Scope></Scope>
<IOProtocol>ap_memory</IOProtocol>
<IOConfig></IOConfig>
<Dir>out</Dir>
<Bits>1</Bits>
<Attribute>control</Attribute>
</RtlPorts>
<RtlPorts>
<name>data_58_q0</name>
<Object>data_58</Object>
<Type>array</Type>
<Scope></Scope>
<IOProtocol>ap_memory</IOProtocol>
<IOConfig></IOConfig>
<Dir>in</Dir>
<Bits>16</Bits>
<Attribute>data</Attribute>
</RtlPorts>
<RtlPorts>
<name>data_59_address0</name>
<Object>data_59</Object>
<Type>array</Type>
<Scope></Scope>
<IOProtocol>ap_memory</IOProtocol>
<IOConfig></IOConfig>
<Dir>out</Dir>
<Bits>7</Bits>
<Attribute>address</Attribute>
</RtlPorts>
<RtlPorts>
<name>data_59_ce0</name>
<Object>data_59</Object>
<Type>array</Type>
<Scope></Scope>
<IOProtocol>ap_memory</IOProtocol>
<IOConfig></IOConfig>
<Dir>out</Dir>
<Bits>1</Bits>
<Attribute>control</Attribute>
</RtlPorts>
<RtlPorts>
<name>data_59_q0</name>
<Object>data_59</Object>
<Type>array</Type>
<Scope></Scope>
<IOProtocol>ap_memory</IOProtocol>
<IOConfig></IOConfig>
<Dir>in</Dir>
<Bits>16</Bits>
<Attribute>data</Attribute>
</RtlPorts>
<RtlPorts>
<name>data_60_address0</name>
<Object>data_60</Object>
<Type>array</Type>
<Scope></Scope>
<IOProtocol>ap_memory</IOProtocol>
<IOConfig></IOConfig>
<Dir>out</Dir>
<Bits>7</Bits>
<Attribute>address</Attribute>
</RtlPorts>
<RtlPorts>
<name>data_60_ce0</name>
<Object>data_60</Object>
<Type>array</Type>
<Scope></Scope>
<IOProtocol>ap_memory</IOProtocol>
<IOConfig></IOConfig>
<Dir>out</Dir>
<Bits>1</Bits>
<Attribute>control</Attribute>
</RtlPorts>
<RtlPorts>
<name>data_60_q0</name>
<Object>data_60</Object>
<Type>array</Type>
<Scope></Scope>
<IOProtocol>ap_memory</IOProtocol>
<IOConfig></IOConfig>
<Dir>in</Dir>
<Bits>16</Bits>
<Attribute>data</Attribute>
</RtlPorts>
<RtlPorts>
<name>data_61_address0</name>
<Object>data_61</Object>
<Type>array</Type>
<Scope></Scope>
<IOProtocol>ap_memory</IOProtocol>
<IOConfig></IOConfig>
<Dir>out</Dir>
<Bits>7</Bits>
<Attribute>address</Attribute>
</RtlPorts>
<RtlPorts>
<name>data_61_ce0</name>
<Object>data_61</Object>
<Type>array</Type>
<Scope></Scope>
<IOProtocol>ap_memory</IOProtocol>
<IOConfig></IOConfig>
<Dir>out</Dir>
<Bits>1</Bits>
<Attribute>control</Attribute>
</RtlPorts>
<RtlPorts>
<name>data_61_q0</name>
<Object>data_61</Object>
<Type>array</Type>
<Scope></Scope>
<IOProtocol>ap_memory</IOProtocol>
<IOConfig></IOConfig>
<Dir>in</Dir>
<Bits>16</Bits>
<Attribute>data</Attribute>
</RtlPorts>
<RtlPorts>
<name>data_62_address0</name>
<Object>data_62</Object>
<Type>array</Type>
<Scope></Scope>
<IOProtocol>ap_memory</IOProtocol>
<IOConfig></IOConfig>
<Dir>out</Dir>
<Bits>7</Bits>
<Attribute>address</Attribute>
</RtlPorts>
<RtlPorts>
<name>data_62_ce0</name>
<Object>data_62</Object>
<Type>array</Type>
<Scope></Scope>
<IOProtocol>ap_memory</IOProtocol>
<IOConfig></IOConfig>
<Dir>out</Dir>
<Bits>1</Bits>
<Attribute>control</Attribute>
</RtlPorts>
<RtlPorts>
<name>data_62_q0</name>
<Object>data_62</Object>
<Type>array</Type>
<Scope></Scope>
<IOProtocol>ap_memory</IOProtocol>
<IOConfig></IOConfig>
<Dir>in</Dir>
<Bits>16</Bits>
<Attribute>data</Attribute>
</RtlPorts>
<RtlPorts>
<name>data_63_address0</name>
<Object>data_63</Object>
<Type>array</Type>
<Scope></Scope>
<IOProtocol>ap_memory</IOProtocol>
<IOConfig></IOConfig>
<Dir>out</Dir>
<Bits>7</Bits>
<Attribute>address</Attribute>
</RtlPorts>
<RtlPorts>
<name>data_63_ce0</name>
<Object>data_63</Object>
<Type>array</Type>
<Scope></Scope>
<IOProtocol>ap_memory</IOProtocol>
<IOConfig></IOConfig>
<Dir>out</Dir>
<Bits>1</Bits>
<Attribute>control</Attribute>
</RtlPorts>
<RtlPorts>
<name>data_63_q0</name>
<Object>data_63</Object>
<Type>array</Type>
<Scope></Scope>
<IOProtocol>ap_memory</IOProtocol>
<IOConfig></IOConfig>
<Dir>in</Dir>
<Bits>16</Bits>
<Attribute>data</Attribute>
</RtlPorts>
<RtlPorts>
<name>data_64_address0</name>
<Object>data_64</Object>
<Type>array</Type>
<Scope></Scope>
<IOProtocol>ap_memory</IOProtocol>
<IOConfig></IOConfig>
<Dir>out</Dir>
<Bits>7</Bits>
<Attribute>address</Attribute>
</RtlPorts>
<RtlPorts>
<name>data_64_ce0</name>
<Object>data_64</Object>
<Type>array</Type>
<Scope></Scope>
<IOProtocol>ap_memory</IOProtocol>
<IOConfig></IOConfig>
<Dir>out</Dir>
<Bits>1</Bits>
<Attribute>control</Attribute>
</RtlPorts>
<RtlPorts>
<name>data_64_q0</name>
<Object>data_64</Object>
<Type>array</Type>
<Scope></Scope>
<IOProtocol>ap_memory</IOProtocol>
<IOConfig></IOConfig>
<Dir>in</Dir>
<Bits>16</Bits>
<Attribute>data</Attribute>
</RtlPorts>
<RtlPorts>
<name>data_65_address0</name>
<Object>data_65</Object>
<Type>array</Type>
<Scope></Scope>
<IOProtocol>ap_memory</IOProtocol>
<IOConfig></IOConfig>
<Dir>out</Dir>
<Bits>7</Bits>
<Attribute>address</Attribute>
</RtlPorts>
<RtlPorts>
<name>data_65_ce0</name>
<Object>data_65</Object>
<Type>array</Type>
<Scope></Scope>
<IOProtocol>ap_memory</IOProtocol>
<IOConfig></IOConfig>
<Dir>out</Dir>
<Bits>1</Bits>
<Attribute>control</Attribute>
</RtlPorts>
<RtlPorts>
<name>data_65_q0</name>
<Object>data_65</Object>
<Type>array</Type>
<Scope></Scope>
<IOProtocol>ap_memory</IOProtocol>
<IOConfig></IOConfig>
<Dir>in</Dir>
<Bits>16</Bits>
<Attribute>data</Attribute>
</RtlPorts>
<RtlPorts>
<name>data_66_address0</name>
<Object>data_66</Object>
<Type>array</Type>
<Scope></Scope>
<IOProtocol>ap_memory</IOProtocol>
<IOConfig></IOConfig>
<Dir>out</Dir>
<Bits>7</Bits>
<Attribute>address</Attribute>
</RtlPorts>
<RtlPorts>
<name>data_66_ce0</name>
<Object>data_66</Object>
<Type>array</Type>
<Scope></Scope>
<IOProtocol>ap_memory</IOProtocol>
<IOConfig></IOConfig>
<Dir>out</Dir>
<Bits>1</Bits>
<Attribute>control</Attribute>
</RtlPorts>
<RtlPorts>
<name>data_66_q0</name>
<Object>data_66</Object>
<Type>array</Type>
<Scope></Scope>
<IOProtocol>ap_memory</IOProtocol>
<IOConfig></IOConfig>
<Dir>in</Dir>
<Bits>16</Bits>
<Attribute>data</Attribute>
</RtlPorts>
<RtlPorts>
<name>data_67_address0</name>
<Object>data_67</Object>
<Type>array</Type>
<Scope></Scope>
<IOProtocol>ap_memory</IOProtocol>
<IOConfig></IOConfig>
<Dir>out</Dir>
<Bits>7</Bits>
<Attribute>address</Attribute>
</RtlPorts>
<RtlPorts>
<name>data_67_ce0</name>
<Object>data_67</Object>
<Type>array</Type>
<Scope></Scope>
<IOProtocol>ap_memory</IOProtocol>
<IOConfig></IOConfig>
<Dir>out</Dir>
<Bits>1</Bits>
<Attribute>control</Attribute>
</RtlPorts>
<RtlPorts>
<name>data_67_q0</name>
<Object>data_67</Object>
<Type>array</Type>
<Scope></Scope>
<IOProtocol>ap_memory</IOProtocol>
<IOConfig></IOConfig>
<Dir>in</Dir>
<Bits>16</Bits>
<Attribute>data</Attribute>
</RtlPorts>
<RtlPorts>
<name>data_68_address0</name>
<Object>data_68</Object>
<Type>array</Type>
<Scope></Scope>
<IOProtocol>ap_memory</IOProtocol>
<IOConfig></IOConfig>
<Dir>out</Dir>
<Bits>7</Bits>
<Attribute>address</Attribute>
</RtlPorts>
<RtlPorts>
<name>data_68_ce0</name>
<Object>data_68</Object>
<Type>array</Type>
<Scope></Scope>
<IOProtocol>ap_memory</IOProtocol>
<IOConfig></IOConfig>
<Dir>out</Dir>
<Bits>1</Bits>
<Attribute>control</Attribute>
</RtlPorts>
<RtlPorts>
<name>data_68_q0</name>
<Object>data_68</Object>
<Type>array</Type>
<Scope></Scope>
<IOProtocol>ap_memory</IOProtocol>
<IOConfig></IOConfig>
<Dir>in</Dir>
<Bits>16</Bits>
<Attribute>data</Attribute>
</RtlPorts>
<RtlPorts>
<name>data_69_address0</name>
<Object>data_69</Object>
<Type>array</Type>
<Scope></Scope>
<IOProtocol>ap_memory</IOProtocol>
<IOConfig></IOConfig>
<Dir>out</Dir>
<Bits>7</Bits>
<Attribute>address</Attribute>
</RtlPorts>
<RtlPorts>
<name>data_69_ce0</name>
<Object>data_69</Object>
<Type>array</Type>
<Scope></Scope>
<IOProtocol>ap_memory</IOProtocol>
<IOConfig></IOConfig>
<Dir>out</Dir>
<Bits>1</Bits>
<Attribute>control</Attribute>
</RtlPorts>
<RtlPorts>
<name>data_69_q0</name>
<Object>data_69</Object>
<Type>array</Type>
<Scope></Scope>
<IOProtocol>ap_memory</IOProtocol>
<IOConfig></IOConfig>
<Dir>in</Dir>
<Bits>16</Bits>
<Attribute>data</Attribute>
</RtlPorts>
</InterfaceSummary>

</profile>
